day_014/moore_consec3Ones/consec3Ones.v
// CONSECUTIVE 3 ONES DETECTING MOORE MACHINE (OVERLAPPING)

module consec_3_ones (
	input wire clk,
	input wire rst,
	input wire bitstream,
	output reg y
);

	localparam S0 = 2'b00;
	localparam S1 = 2'b01;
	localparam S2 = 2'b10;
	localparam S3 = 2'b11;

	reg [1:0] curr_state, next_state;

	// sequential logic
	always @(posedge clk or posedge rst) begin
		if (rst) begin
			curr_state <= S0;
		end
		else begin
			curr_state <= next_state;
		end
	end

	// combinational (next state) logic
	always @(*) begin
		// to avoid latches
		next_state = curr_state;
		y = (curr_state == S3) ? 1'b1 : 1'b0;

		case (curr_state)
			S0 : next_state = (bitstream == 1'b1) ? S1 : S0;
			S1 : next_state = (bitstream == 1'b1) ? S2 : S0;
			S2 : next_state = (bitstream == 1'b1) ? S3 : S0;
			S3 : next_state = (bitstream == 1'b1) ? S3 : S0;  // Detects overlap
			default : next_state = S0;
		endcase
	end

endmodule

day_014/moore_consec3Ones/consec3OnesTB.v
// TESTBENCH FOR
// CONSECUTIVE 3 ONES DETECTING MEALY MACHINE (OVERLAPPING)

`timescale 1ns / 1ps

module consec_3_ones_tb;

	reg  clk;
	reg  rst;
	reg  bitstream;
	wire y;

	reg [9:0] pattern;
	integer i;

	consec_3_ones uut (.clk(clk), .rst(rst), .bitstream(bitstream), .y(y));

	initial begin
		clk = 0;
		forever #1 clk = ~clk;
	end

	initial begin
		$timeformat (-9, 0, "", 5);
		pattern = 10'b01_1001_1110;

		$dumpfile ("consec3OnesTB.vcd");
		$dumpvars (0, consec_3_ones_tb);

		$display ("\nCONSECUTIVE 3 ONES DETECTING MOORE MACHINE (OVERLAPPING)\n");
		$monitor ("Time=%0t, rst=%b, bitstream=%b, y=%b", $time, rst, bitstream, y);

		rst = 1'b1;
		bitstream = 1'b0;

		@(negedge clk);
		rst = 1'b0;

		for (i=9; i>=0; i--) begin
			@(posedge clk);
			bitstream <= pattern[i];
		end

		@(posedge clk);
		#1;
		$display ("\nSIM FIN");
		$finish;
	end

endmodule

day_014/moore_consec3Ones/consec3OnesTB.vcd
$date
	Mon Jul  6 23:53:03 2026
$end
$version
	Icarus Verilog
$end
$timescale
	1ps
$end
$scope module consec_3_ones_tb $end
$var wire 1 ! y $end
$var reg 1 " bitstream $end
$var reg 1 # clk $end
$var reg 10 $ pattern [9:0] $end
$var reg 1 % rst $end
$var integer 32 & i [31:0] $end
$scope module uut $end
$var wire 1 " bitstream $end
$var wire 1 # clk $end
$var wire 1 % rst $end
$var parameter 2 ' S0 $end
$var parameter 2 ( S1 $end
$var parameter 2 ) S2 $end
$var parameter 2 * S3 $end
$var reg 2 + curr_state [1:0] $end
$var reg 2 , next_state [1:0] $end
$var reg 1 ! y $end
$upscope $end
$upscope $end
$enddefinitions $end
$comment Show the parameter values. $end
$dumpall
b11 *
b10 )
b1 (
b0 '
$end
#0
$dumpvars
b0 ,
b0 +
bx &
1%
b110011110 $
0#
0"
0!
$end
#1000
1#
#2000
b1001 &
0%
0#
#3000
b1000 &
1#
#4000
0#
#5000
b1 ,
1"
b111 &
1#
#6000
0#
#7000
b10 ,
b1 +
b110 &
1#
#8000
0#
#9000
b0 ,
b10 +
0"
b101 &
1#
#10000
0#
#11000
b0 +
b100 &
1#
#12000
0#
#13000
b1 ,
1"
b11 &
1#
#14000
0#
#15000
b10 ,
b1 +
b10 &
1#
#16000
0#
#17000
b11 ,
b10 +
b1 &
1#
#18000
0#
#19000
1!
b11 +
b0 &
1#
#20000
0#
#21000
b0 ,
0"
b11111111111111111111111111111111 &
1#
#22000
0#
#23000
0!
b0 +
1#
