day_015/lightFlasher/timer.v
`timescale 1ns / 1ps

module timer (
	input wire clk,
	input wire rst,
	input wire timer_en,
	input wire timer_mode,
	output wire timer_done
);

	localparam T_LIGHT_OFF = 3'b011,
		   T_LIGHT_ON  = 3'b101;

	reg [2:0] curr_count_r;
	reg [2:0] next_count_ns;

	always @(posedge clk or posedge rst) begin
		if (rst) curr_count_r <= 3'b000;
		else	 curr_count_r <= next_count_ns;
	end

	assign timer_done = !(|curr_count_r);	// `timer_done` goes HIGH when `curr_count_r = T0`

	always @(*) begin
		casez ({rst, timer_en, timer_mode, timer_done})
			4'b1??? : next_count_ns = 3'b000;
			4'b010? : next_count_ns = T_LIGHT_OFF;
			4'b011? : next_count_ns = T_LIGHT_ON;
			4'b00?0 : next_count_ns = curr_count_r - 1'b1;
			4'b00?1 : next_count_ns = curr_count_r;
			default : next_count_ns = curr_count_r;
		endcase
	end

endmodule

day_015/lightFlasher/lightFlasher.v
`timescale 1ns / 1ps

module light_flasher (
	input wire clk,
	input wire rst,
	input wire flash_req,
	output reg light_out
);

	localparam S_OFF    = 3'b000,
		   S_HIGH_1 = 3'b001,
		   S_LOW_1  = 3'b010,
		   S_HIGH_2 = 3'b011,
		   S_LOW_2  = 3'b100,
		   S_HIGH_3 = 3'b101;

	reg [2:0] curr_state_r;
	reg [2:0] next_state_ns;

	reg timer_en;
	reg timer_mode;
	wire timer_done;

	always @(posedge clk or posedge rst) begin
		if (rst) curr_state_r <= S_OFF;
		else	 curr_state_r <= next_state_ns;
	end

	timer t1 (
		.clk(clk),
		.rst(rst),
		.timer_en(timer_en),
		.timer_mode(timer_mode),
		.timer_done(timer_done)
	);

	always @(*) begin
		// to avoid unintentional latches
		next_state_ns = curr_state_r;
		timer_mode    = 1'b0;
		light_out     = 1'b0;
		timer_en      = 1'b0;

		(* parallel_case *)
		case (curr_state_r)
			S_OFF : begin
				next_state_ns = (flash_req) ? S_HIGH_1 : S_OFF;
				timer_mode    = 1'b1;
				timer_en      = 1'b1;
				light_out     = 1'b0;
			end

			S_HIGH_1 : begin
				if (timer_done) begin
					next_state_ns = S_LOW_1;
					timer_mode = 1'b0;
				end
				else begin
					next_state_ns = S_HIGH_1;
				end
				timer_en      = timer_done;
				light_out     = 1'b1;
			end

			S_LOW_1 : begin
				if (timer_done) begin
					next_state_ns = S_HIGH_2;
					timer_mode    = 1'b1;
				end 
				else begin
					next_state_ns = S_LOW_1;
				end
				timer_en      = timer_done;
				light_out     = 1'b0;
			end

			S_HIGH_2 : begin
				if (timer_done) begin
					next_state_ns = S_LOW_2;
					timer_mode    = 1'b0;
				end
				else begin
					next_state_ns = S_HIGH_2;
				end
				timer_en      = timer_done;
				light_out     = 1'b1;
			end

			S_LOW_2 : begin
				if (timer_done) begin
					next_state_ns = S_HIGH_3;
					timer_mode = 1'b1;
				end
				else begin
					next_state_ns = S_LOW_2;
				end
				timer_en      = timer_done;
				light_out     = 1'b0;
			end

			S_HIGH_3 : begin
				if (timer_done) begin
					next_state_ns = S_OFF;
					timer_mode = 1'b0;
				end
				else begin
					next_state_ns = S_HIGH_3;
				end
				timer_en      = timer_done;
				light_out     = 1'b1;
			end

			default : begin
				next_state_ns = S_OFF;
				timer_mode    = 1'b0;
				timer_en      = 1'b0;
				light_out     = 1'b0;
			end
		endcase
	end

endmodule

day_015/lightFlasher/lightFlasherTB.v
`timescale 1ns / 1ps

module light_flasher_tb;

	reg  clk;
	reg  rst;
	reg  flash_req;
	wire light_out;

	light_flasher uut (
		.clk(clk),
		.rst(rst),
		.flash_req(flash_req),
		.light_out(light_out)
	);

	initial begin
		clk = 0;
		forever #1 clk = ~clk;
	end

	initial begin
		$timeformat (-9, 0, "", 5);

		$dumpfile ("lightFlasherTB.vcd");
		$dumpvars (0, light_flasher_tb);

		$display ("\nLIGHT FLASHER: FACTORED FSM\n");
		$monitor ("Time=%0t, rst=%b, flash_req=%b, light_out=%b", $time, rst, flash_req, light_out);

		rst       = 1'b1;
		flash_req = 1'bx;

		@(negedge clk);
		rst       = 1'b0;
		flash_req = 1'b1;

		@(negedge clk);
		flash_req = 1'b0;

		@(posedge clk);
		#57;
		$display ("\nSIM FIN");
		$finish;
	end

endmodule

day_015/lightFlasher/lightFlasherTB.vcd
$date
	Fri Jul 10 00:03:44 2026
$end
$version
	Icarus Verilog
$end
$timescale
	1ps
$end
$scope module light_flasher_tb $end
$var wire 1 ! light_out $end
$var reg 1 " clk $end
$var reg 1 # flash_req $end
$var reg 1 $ rst $end
$scope module uut $end
$var wire 1 " clk $end
$var wire 1 # flash_req $end
$var wire 1 $ rst $end
$var wire 1 % timer_done $end
$var parameter 3 & S_HIGH_1 $end
$var parameter 3 ' S_HIGH_2 $end
$var parameter 3 ( S_HIGH_3 $end
$var parameter 3 ) S_LOW_1 $end
$var parameter 3 * S_LOW_2 $end
$var parameter 3 + S_OFF $end
$var reg 3 , curr_state_r [2:0] $end
$var reg 1 ! light_out $end
$var reg 3 - next_state_ns [2:0] $end
$var reg 1 . timer_en $end
$var reg 1 / timer_mode $end
$scope module t1 $end
$var wire 1 " clk $end
$var wire 1 $ rst $end
$var wire 1 . timer_en $end
$var wire 1 / timer_mode $end
$var wire 1 % timer_done $end
$var parameter 3 0 T_LIGHT_OFF $end
$var parameter 3 1 T_LIGHT_ON $end
$var reg 3 2 curr_count_r [2:0] $end
$var reg 3 3 next_count_ns [2:0] $end
$upscope $end
$upscope $end
$upscope $end
$enddefinitions $end
$comment Show the parameter values. $end
$dumpall
b101 1
b11 0
b0 +
b100 *
b10 )
b101 (
b11 '
b1 &
$end
#0
$dumpvars
b0 3
b0 2
1/
1.
b0x -
b0 ,
1%
1$
x#
0"
0!
$end
#1000
1"
#2000
1.
1/
b1 -
b101 3
1#
0$
0"
#3000
b100 3
1!
0.
0/
0%
b101 2
b1 ,
1"
#4000
1!
0#
0"
#5000
b11 3
b100 2
1"
#6000
0"
#7000
b10 3
b11 2
1"
#8000
0"
#9000
b1 3
b10 2
1"
#10000
0"
#11000
b0 3
b1 2
1"
#12000
0"
#13000
b11 3
1.
b10 -
1!
1%
b0 2
1"
#14000
0"
#15000
b10 3
0.
0!
0%
b11 2
b10 ,
1"
#16000
0"
#17000
b1 3
b10 2
1"
#18000
0"
#19000
b0 3
b1 2
1"
#20000
0"
#21000
b101 3
1.
1/
b11 -
1%
b0 2
1"
#22000
0"
#23000
b100 3
1!
0.
0/
0%
b101 2
b11 ,
1"
#24000
0"
#25000
b11 3
b100 2
1"
#26000
0"
#27000
b10 3
b11 2
1"
#28000
0"
#29000
b1 3
b10 2
1"
#30000
0"
#31000
b0 3
b1 2
1"
#32000
0"
#33000
b11 3
1.
b100 -
1!
1%
b0 2
1"
#34000
0"
#35000
b10 3
0.
0!
0%
b11 2
b100 ,
1"
#36000
0"
#37000
b1 3
b10 2
1"
#38000
0"
#39000
b0 3
b1 2
1"
#40000
0"
#41000
b101 3
1.
1/
b101 -
1%
b0 2
1"
#42000
0"
#43000
b100 3
1!
0.
0/
0%
b101 2
b101 ,
1"
#44000
0"
#45000
b11 3
b100 2
1"
#46000
0"
#47000
b10 3
b11 2
1"
#48000
0"
#49000
b1 3
b10 2
1"
#50000
0"
#51000
b0 3
b1 2
1"
#52000
0"
#53000
b11 3
1.
b0 -
1!
1%
b0 2
1"
#54000
0"
#55000
b101 3
1/
1.
0!
0%
b11 2
b0 ,
1"
#56000
0"
#57000
b101 2
1"
