day_016/fifo.v
`timescale 1ns / 1ps

/*
*
* It is better to keep `DEPTH` a power of 2 for efficient pointer management.
* I'm using DEPTH = 16
*
* The FIFO has following inputs and outputs:
	* INPUTS ---
		* clk_i     -> common FIFO clock
		* rst_n_i   -> active-low reset
		* wr_data_i -> this will be a vector of width `WIDTH`
		* wr_en_i   -> this is a flag used to allow writing to FIFO
		* rd_en_i   -> this is a flag used to allow reading from FIFO
	* OUTPUTS ---
		* full_o    -> this flag is used to indicate if FIFO is full
		* rd_data_o -> this will be a vector of width `WIDTH`
		* empty_o   -> this flag is used to indicate if FIFO is empty
* 
*/

module fifo #(
	parameter WIDTH = 32,	// data width
	parameter DEPTH = 16	// number of elements of that width
) (
	// ----------------------------------------------------------------------------------
	// clock & reset
	input wire clk_i,
	input wire rst_n_i,
	// ----------------------------------------------------------------------------------
	// write
	input wire	       wr_en_i,
	input wire [WIDTH-1:0] wr_data_i,
	output wire	       full_o,
	// ----------------------------------------------------------------------------------
	// read
	input wire 	       rd_en_i,
	output reg [WIDTH-1:0] rd_data_o,
	output wire 	       empty_o
);

	// ADDRESS WIDTH CALC ---
	localparam ADDR_WIDTH = $clog2 (DEPTH);

	// ADDRESS POINTERS ----
	reg [ADDR_WIDTH-1:0] wr_ptr;
	reg [ADDR_WIDTH-1:0] rd_ptr;

	// FLAGS ---
	reg last_operation_flag;	// write -> 0; read -> 1

	// MEMORY/REGISTER ---
	reg [WIDTH-1:0] memory [0:DEPTH-1];
	
	// ----------------------------------------------------------------------------------
	// write operation
	always @(posedge clk_i or negedge rst_n_i) begin
		if (!rst_n_i) begin
			wr_ptr <= {ADDR_WIDTH{1'b0}};
		end
		else if (wr_en_i & !full_o) begin
			memory[wr_ptr] <= wr_data_i;
			wr_ptr <= wr_ptr + 1'b1;
		end
	end

	// ----------------------------------------------------------------------------------
	// read operation
	always @(posedge clk_i or negedge rst_n_i) begin
		if (!rst_n_i) begin
			rd_ptr <= {ADDR_WIDTH{1'b0}};
		end
		else if (rd_en_i & !empty_o) begin
			rd_data_o <= memory[rd_ptr];
			rd_ptr <= rd_ptr + 1'b1;
		end
	end

	// ----------------------------------------------------------------------------------
	// checking which operation happened last
	always @(posedge clk_i or negedge rst_n_i) begin
		if (!rst_n_i) begin
			last_operation_flag <= 1'b1;
		end
		else if (wr_en_i & !full_o) begin
			last_operation_flag <= 1'b0;
		end
		else if (rd_en_i & !empty_o) begin
			last_operation_flag <= 1'b1;
		end
	end

	// ----------------------------------------------------------------------------------
	// updating `full_o` and `empty_o` flags
	assign full_o  = ((wr_ptr == rd_ptr) & !last_operation_flag);
	assign empty_o = ((wr_ptr == rd_ptr) & last_operation_flag);

endmodule

day_016/fifoTB.v
`timescale 1ns / 1ps

module fifo_tb;

	// ----------------------------------------------------------------------------------
	// parameters for memory
	parameter WIDTH = 32;
	parameter DEPTH = 16;

	// ----------------------------------------------------------------------------------
	// clock & reset
	reg clk;
	reg rst_n_i;

	// ----------------------------------------------------------------------------------
	// write
	reg 		 wr_en_i;
	reg  [WIDTH-1:0] wr_data_i;
	wire 		 full_o;

	// ----------------------------------------------------------------------------------
	// read
	reg 		 rd_en_i;
	wire [WIDTH-1:0] rd_data_o;
	wire 		 empty_o;
	
	// ----------------------------------------------------------------------------------
	// required variables
	// reg [WIDTH-1:0] pattern;	// used for `wr_data_i`
	integer i;

	// ----------------------------------------------------------------------------------
	// the UUT
	fifo #(
		.WIDTH(WIDTH),
		.DEPTH(DEPTH)
	) uut (
		.clk_i(clk),
		.rst_n_i(rst_n_i),
		.wr_en_i(wr_en_i),
		.wr_data_i(wr_data_i),
		.full_o(full_o),
		.rd_en_i(rd_en_i),
		.rd_data_o(rd_data_o),
		.empty_o(empty_o)
	);

	initial begin
		clk = 0;
		forever #1 clk = ~clk;
	end

	initial begin
		$timeformat (-9, 0, "", 5);

		$dumpfile ("fifoTB.vcd");
		$dumpvars (0, fifo_tb);

		$display ("\nFIFO - WRITE & READ WITH SAME CLOCK\n");
		$display (" Time | rst_n | wr_en |   wr_data   | rd_en |   rd_data   | full | empty ");
		$display ("------|-------|-------|-------------|-------|-------------|------|-------");
		$monitor ("   %0t  |   %b   |   %b   |  %0h   |   %b   |  %0h   |   %b  |   %b  ", $time, rst_n_i, wr_en_i, wr_data_i, rd_en_i, rd_data_o, full_o, empty_o);

		rst_n_i = 1'b0;
		wr_data_i = {WIDTH{1'bx}};

		@(negedge clk);
		rst_n_i   = 1'b1;
		wr_data_i = $urandom_range (0, 2**(WIDTH)-1);
		wr_en_i   = 1'b0;
		rd_en_i   = 1'b0;
		
		repeat(2) @(negedge clk);
		rd_en_i = 1'b1;

		repeat(2) @(negedge clk);
		rd_en_i = 1'b0;
		wr_en_i = 1'b1;

		repeat(2) @(negedge clk);
		wr_en_i = 1'b0;

		for (i=0; i<10; i++) begin
			@(negedge clk);
			wr_data_i = $urandom_range (0, 2**(WIDTH)-1);

			if (i == 3) wr_en_i = 1'b1;

			if (i == 7) rd_en_i = 1'b1;
		end

		repeat(5) @(negedge clk);
		rd_en_i = 1'b0;

		@(posedge clk);
		@(negedge clk);
		$display ("\nSIM FIN");
		$finish;
	end

endmodule

day_016/fifoTB.vcd
$date
	Fri Jul 10 23:30:53 2026
$end
$version
	Icarus Verilog
$end
$timescale
	1ps
$end
$scope module fifo_tb $end
$var wire 32 ! rd_data_o [31:0] $end
$var wire 1 " full_o $end
$var wire 1 # empty_o $end
$var parameter 32 $ DEPTH $end
$var parameter 32 % WIDTH $end
$var reg 1 & clk $end
$var reg 1 ' rd_en_i $end
$var reg 1 ( rst_n_i $end
$var reg 32 ) wr_data_i [31:0] $end
$var reg 1 * wr_en_i $end
$var integer 32 + i [31:0] $end
$scope module uut $end
$var wire 1 & clk_i $end
$var wire 1 # empty_o $end
$var wire 1 " full_o $end
$var wire 1 ' rd_en_i $end
$var wire 1 ( rst_n_i $end
$var wire 32 , wr_data_i [31:0] $end
$var wire 1 * wr_en_i $end
$var parameter 32 - ADDR_WIDTH $end
$var parameter 32 . DEPTH $end
$var parameter 32 / WIDTH $end
$var reg 1 0 last_operation_flag $end
$var reg 32 1 rd_data_o [31:0] $end
$var reg 4 2 rd_ptr [3:0] $end
$var reg 4 3 wr_ptr [3:0] $end
$upscope $end
$upscope $end
$enddefinitions $end
$comment Show the parameter values. $end
$dumpall
b100000 /
b10000 .
b100 -
b100000 %
b10000 $
$end
#0
$dumpvars
b0 3
b0 2
bx 1
10
bx ,
bx +
x*
bx )
0(
x'
0&
1#
0"
bx !
$end
#1000
1&
#2000
0'
0*
b10010010000101010011010100100100 )
b10010010000101010011010100100100 ,
1(
0&
#3000
1&
#4000
0&
#5000
1&
#6000
1'
0&
#7000
1&
#8000
0&
#9000
1&
#10000
1*
0'
0&
#11000
0#
b1 3
00
1&
#12000
0&
#13000
b10 3
1&
#14000
b0 +
0*
0&
#15000
1&
#16000
b1 +
b1000000100010010101111010000001 )
b1000000100010010101111010000001 ,
0&
#17000
1&
#18000
b10 +
b100100001001101011000001001 )
b100100001001101011000001001 ,
0&
#19000
1&
#20000
b11 +
b110001111100000101011001100011 )
b110001111100000101011001100011 ,
0&
#21000
1&
#22000
b100 +
1*
b10000110101110010111101100001101 )
b10000110101110010111101100001101 ,
0&
#23000
b11 3
1&
#24000
b101 +
b11000110110111111001100110001101 )
b11000110110111111001100110001101 ,
0&
#25000
b100 3
1&
#26000
b110 +
b110010110000101000010001100101 )
b110010110000101000010001100101 ,
0&
#27000
b101 3
1&
#28000
b111 +
b1001001101110101001000010010 )
b1001001101110101001000010010 ,
0&
#29000
b110 3
1&
#30000
b1000 +
1'
b10000000111100111110001100000001 )
b10000000111100111110001100000001 ,
0&
#31000
b111 3
b1 2
b10010010000101010011010100100100 !
b10010010000101010011010100100100 1
1&
#32000
b1001 +
b10000110110101111100110100001101 )
b10000110110101111100110100001101 ,
0&
#33000
b10 2
b1000 3
1&
#34000
b1010 +
b10111011001000111111000101110110 )
b10111011001000111111000101110110 ,
0&
#35000
b1001 3
b11 2
b10000110101110010111101100001101 !
b10000110101110010111101100001101 1
1&
#36000
0&
#37000
b100 2
b11000110110111111001100110001101 !
b11000110110111111001100110001101 1
b1010 3
1&
#38000
0&
#39000
b1011 3
b101 2
b110010110000101000010001100101 !
b110010110000101000010001100101 1
1&
#40000
0&
#41000
b110 2
b1001001101110101001000010010 !
b1001001101110101001000010010 1
b1100 3
1&
#42000
0&
#43000
b1101 3
b111 2
b10000000111100111110001100000001 !
b10000000111100111110001100000001 1
1&
#44000
0'
0&
#45000
b1110 3
1&
