day_016/syncFifo.v
`timescale 1ns / 1ps

module sync_fifo #(
	parameter WIDTH = 8,
	parameter DEPTH = 16
) (
	input wire	       clk,
	input wire	       rst,
	input wire	       wr_en,
	input wire	       rd_en,
	input wire [WIDTH-1:0] wr_data,
   	output reg [WIDTH-1:0] rd_data,
   	output reg             empty,
	output reg             full
);

	reg [WIDTH-1:0] mem [0:DEPTH-1];
   	reg [WIDTH-1:0] rd_ptr = 0;
	reg [WIDTH-1:0] wr_ptr = 0;
   	reg [WIDTH-1:0] next_wr_ptr;
   	reg [WIDTH-1:0] next_rd_ptr;
   	reg [DEPTH-1:0] num_items = 0;

   	always @(posedge clk) begin
        	if (rst) begin
	         	rd_ptr <= 0;
	         	wr_ptr <= 0;
	         	next_rd_ptr <= 0;
	         	next_wr_ptr <= 0;
	         	num_items <= 0;
	         	empty <= 1;
	         	full <= 0;
	      	end
        	else begin
	         	rd_ptr <= next_rd_ptr;
	         	wr_ptr <= next_wr_ptr;
	         	empty <= (num_items == 0);
	         	full <= (num_items == DEPTH);

	        	if (wr_en && !full) begin
	            		mem[wr_ptr] <= wr_data;
	            		next_wr_ptr <= (wr_ptr + 1) % DEPTH;
	            		num_items <= num_items + 1;
	         	end

	         	if (rd_en && !empty) begin
	            		rd_data <= mem[rd_ptr];
	            		next_rd_ptr <= (rd_ptr + 1) % DEPTH;
	            		num_items <= num_items - 1;
	         	end
		end
    	end

endmodule

day_016/syncFifoTB.v
`timescale 1ns / 1ps

module sync_fifo_tb;

	localparam WIDTH = 8;
	localparam DEPTH = 16;

   	reg clk;
	reg rst;
	reg wr_en;
	reg rd_en;
   	reg [WIDTH-1:0] wr_data;
   	wire [WIDTH-1:0] rd_data;
   	wire empty, full;

	sync_fifo #(
	   	.WIDTH(WIDTH),
		.DEPTH(DEPTH)
   	) uut (
		.clk(clk),
	   	.rst(rst),
	   	.wr_en(wr_en),
	   	.rd_en(rd_en),
	   	.wr_data(wr_data),
	   	.rd_data(rd_data),
	   	.empty(empty),
	   	.full(full)
   	);
   
   	initial begin 
   		clk= 0;
   		forever #5 clk = ~clk;
   	end
   
    	initial begin
		$dumpfile ("syncFifoTB.vcd");
		$dumpvars (0, sync_fifo_tb);

		$display ("\nSYNCHRONOUS FIFO\n");

		rst = 1;
	        wr_en = 0;
	        rd_en = 0;
	        wr_data = 0;
	      	#10 rst = 0;
	      	#10 wr_en = 1; wr_data = 1;
	      	#10 wr_en = 1; wr_data = 2;
	      	#10 wr_en = 1; wr_data = 3;
	      	#10 rd_en = 1;
	      	#10 rd_en = 1;
	      	#10 wr_en = 1; wr_data = 4;
	      	#10 wr_en = 1; wr_data = 5;
	      	#80 $display ("\nSIM FIN");
		$finish;
    	end
    
   	always @(posedge clk) begin
      		$monitor("RD Data: %d, Empty: %d, Full: %d", rd_data, empty, full);
   	end

endmodule

day_016/syncFifoTB.vcd
$date
	Wed Jul  8 23:50:23 2026
$end
$version
	Icarus Verilog
$end
$timescale
	1ps
$end
$scope module sync_fifo_tb $end
$var wire 8 ! rd_data [7:0] $end
$var wire 1 " full $end
$var wire 1 # empty $end
$var parameter 32 $ DEPTH $end
$var parameter 32 % WIDTH $end
$var reg 1 & clk $end
$var reg 1 ' rd_en $end
$var reg 1 ( rst $end
$var reg 8 ) wr_data [7:0] $end
$var reg 1 * wr_en $end
$scope module uut $end
$var wire 1 & clk $end
$var wire 1 ' rd_en $end
$var wire 1 ( rst $end
$var wire 8 + wr_data [7:0] $end
$var wire 1 * wr_en $end
$var parameter 32 , DEPTH $end
$var parameter 32 - WIDTH $end
$var reg 1 # empty $end
$var reg 1 " full $end
$var reg 8 . next_rd_ptr [7:0] $end
$var reg 8 / next_wr_ptr [7:0] $end
$var reg 16 0 num_items [15:0] $end
$var reg 8 1 rd_data [7:0] $end
$var reg 8 2 rd_ptr [7:0] $end
$var reg 8 3 wr_ptr [7:0] $end
$upscope $end
$upscope $end
$enddefinitions $end
$comment Show the parameter values. $end
$dumpall
b1000 -
b10000 ,
b1000 %
b10000 $
$end
#0
$dumpvars
b0 3
b0 2
bx 1
b0 0
bx /
bx .
b0 +
0*
b0 )
1(
0'
0&
x#
x"
bx !
$end
#5000
0"
1#
b0 /
b0 .
1&
#10000
0&
0(
#15000
1&
#20000
0&
b1 )
b1 +
1*
#25000
b1 0
b1 /
1&
#30000
0&
b10 )
b10 +
#35000
b10 0
0#
b1 3
1&
#40000
0&
b11 )
b11 +
#45000
b11 0
b10 /
1&
#50000
0&
1'
#55000
b1 .
b10 !
b10 1
b10 0
b10 3
1&
#60000
0&
#65000
b1 0
b11 /
b1 2
1&
#70000
0&
b100 )
b100 +
#75000
b10 .
b11 !
b11 1
b0 0
b11 3
1&
#80000
0&
b101 )
b101 +
#85000
b1111111111111111 0
b100 /
1#
b10 2
1&
#90000
0&
#95000
b0 0
0#
b100 3
1&
#100000
0&
#105000
b11 .
b100 !
b100 1
b1111111111111111 0
b101 /
1#
1&
#110000
0&
#115000
b0 0
0#
b101 3
b11 2
1&
#120000
0&
#125000
b100 .
b101 !
b101 1
b1111111111111111 0
b110 /
1#
1&
#130000
0&
#135000
b0 0
0#
b110 3
b100 2
1&
#140000
0&
#145000
b101 .
b1111111111111111 0
b111 /
1#
1&
#150000
0&
#155000
b0 0
0#
b111 3
b101 2
1&
