day_017/multiBitCDC/rd_ptr.v
`timescale 1ns / 1ps

module RD_PTR #(
	parameter ADDR_WIDTH = 4
) (
	input wire 		   clk,
	input wire 		   rst_n,
	input wire 		   rd_en,
	input wire [ADDR_WIDTH:0] g_wr_ptr_sync,

	output reg  [ADDR_WIDTH:0] rd_ptr,
	output wire [ADDR_WIDTH:0] g_rd_ptr,
	output wire 		   empty
);

	assign g_rd_ptr = (rd_ptr >> 1) ^ rd_ptr;

	always @(posedge clk or negedge rst_n) begin
		if (!rst_n) begin
			rd_ptr <= {(ADDR_WIDTH+1){1'b0}};
		end
		else if (rd_en & !empty) begin
			rd_ptr <= rd_ptr + 1'b1;
		end
	end

	assign empty = (g_rd_ptr == g_wr_ptr_sync);

endmodule

day_017/multiBitCDC/wr_ptr.v
`timescale 1ns / 1ps

module WR_PTR #(
	parameter ADDR_WIDTH = 4
) (
	input  wire 		   clk,
	input  wire 		   rst_n,
	input  wire 		   wr_en,
	input  wire [ADDR_WIDTH:0] g_rd_ptr_sync,

	output reg  [ADDR_WIDTH:0] wr_ptr,
	output wire [ADDR_WIDTH:0] g_wr_ptr,
	output wire 		   full
);

	assign g_wr_ptr = (wr_ptr >> 1) ^ wr_ptr;

	always @(posedge clk or negedge rst_n) begin
		if (!rst_n) begin
			wr_ptr   <= {(ADDR_WIDTH+1){1'b0}};
		end
		else if (wr_en & !full) begin
			wr_ptr <= wr_ptr + 1'b1;
		end
	end

	assign full = (g_wr_ptr[ADDR_WIDTH:ADDR_WIDTH-1] == ~g_rd_ptr_sync[ADDR_WIDTH:ADDR_WIDTH-1]) &
		      (g_wr_ptr[ADDR_WIDTH-2:0] == g_rd_ptr_sync[ADDR_WIDTH-2:0]);

endmodule

day_017/multiBitCDC/multiBitCDC.v
`timescale 1ns / 1ps

module multi_bit_cdc #(
	parameter WIDTH = 32,
	parameter DEPTH = 16
) (
	// ------------------------------
	// clocks and reset
	input wire wr_clk_i,
	input wire rd_clk_i,
	input wire wr_rst_n_i,
	input wire rd_rst_n_i,
	// ------------------------------
	// write
	input wire 	       wr_en_i,
	input wire [WIDTH-1:0] wr_data_i,
	output wire 	       full_o,
	// ------------------------------
	// read
	input wire 	       rd_en_i,
	output reg [WIDTH-1:0] rd_data_o,
	output wire	       empty_o
);

	// ------------------------------------------------------
	// for the pointers to be able to address the fifo memory
	localparam ADDR_WIDTH = $clog2 (DEPTH);

	// --------------------------------------------------------------------------------------
	// read and write pointers: binary, gray and synchronized
	// the pointers are assigned an extra bit to allow for smoother
	// calculation of which operation happened last (write, read)
	wire [ADDR_WIDTH:0] wr_ptr;		// binary write ptr
	wire [ADDR_WIDTH:0] rd_ptr;		// binary read ptr
	wire [ADDR_WIDTH:0] g_wr_ptr;		// gray write ptr
	wire [ADDR_WIDTH:0] g_rd_ptr;		// gray read ptr
	reg  [ADDR_WIDTH:0] g_wr_ptr_sync;	// synchronized gray write ptr for cdc - FLOP O/P
	reg  [ADDR_WIDTH:0] g_rd_ptr_sync;	// synchronized gray read ptr for cdc - FLOP O/P

	// ----------------------------
	// memory
	reg [WIDTH-1:0] memory [0:DEPTH-1];

	// ---------------------------------------------------------------------------
	// registers acting as o/p of flops (for CDC)
	reg [ADDR_WIDTH:0] g_wr_ptr_q;		// first flop's output for write
	reg [ADDR_WIDTH:0] g_rd_ptr_q;		// first flop's output for read
	// `g_wr_ptr_q` will be the i/p to 2nd flop, whose o/p will be `g_wr_ptr_sync`
	// `g_rd_ptr_q` will be the i/p to 2nd flop, whose o/p will be `g_rd_ptr_sync`

	// --------------------------------------------------------------------------------------
	// write pointer function instance
	// --------------------------------------------------------------------------------------
	WR_PTR wr_ptr_inst (
		.clk(wr_clk_i), .rst_n(wr_rst_n_i),
		.wr_en(wr_en_i), .wr_ptr(wr_ptr),
		.g_wr_ptr(g_wr_ptr), .g_rd_ptr_sync(g_rd_ptr_sync),
		.full(full_o)
	);

	// --------------------------------------------------------------------------------------
	// read pointer function instance
	// --------------------------------------------------------------------------------------
	RD_PTR rd_ptr_inst (
		.clk(rd_clk_i), .rst_n(rd_rst_n_i),
		.rd_en(rd_en_i), .rd_ptr(rd_ptr),
		.g_rd_ptr(g_rd_ptr), .g_wr_ptr_sync(g_wr_ptr_sync),
		.empty(empty_o)
	);

	// --------------------------------------------------------------------------------------
	// dual flops using `always` block
	// --------------------------------------------------------------------------------------
	// these will be used to allow cdc of the gray-coded pointer values
	// input to flop    -> gray-coded pointer values
	// output from flop -> gray-coded synchronized pointer values
	// - - - - - - - - - - - - - - - - - - - - - - - - - - - - - - - - - - - - - - - - - - - 
	// flop controlled by clock on side of 'write' function
	// - - - - - - - - - - - - - - - - - - - - - - - - - - - - - - - - - - - - - - - - - - - 
	// this is used to synchronize the 'read' gray-coded pointers to its clock
	always @(posedge wr_clk_i or negedge wr_rst_n_i) begin
		if (!wr_rst_n_i) begin
			g_rd_ptr_q    <= {(ADDR_WIDTH+1){1'b0}};
			g_rd_ptr_sync <= {(ADDR_WIDTH+1){1'b0}};
		end
		else begin
			g_rd_ptr_q    <= g_rd_ptr;
			g_rd_ptr_sync <= g_rd_ptr_q;
		end
	end

	// - - - - - - - - - - - - - - - - - - - - - - - - - - - - - - - - - - - - - - - - - - - 
	// flop controlled by clock on side of 'read' domain
	// - - - - - - - - - - - - - - - - - - - - - - - - - - - - - - - - - - - - - - - - - - - 
	// this is used to synchronize the 'write' gray-coded pointers to its clock
	always @(posedge rd_clk_i or negedge rd_rst_n_i) begin
		if (!rd_rst_n_i) begin
			g_wr_ptr_q    <= {(ADDR_WIDTH+1){1'b0}};
			g_wr_ptr_sync <= {(ADDR_WIDTH+1){1'b0}};
		end
		else begin			
			g_wr_ptr_q    <= g_wr_ptr;
			g_wr_ptr_sync <= g_wr_ptr_q;
		end
	end

	// --------------------------------------------------------------------------------------
	// storing data values inside of FIFO (WRITE OPERATION)
	// --------------------------------------------------------------------------------------
	always @(posedge wr_clk_i) begin
		if (wr_en_i & !full_o) begin
			memory[wr_ptr[ADDR_WIDTH-1:0]] <= wr_data_i;
		end
	end

	// --------------------------------------------------------------------------------------
	// reading data values from FIFO (READ OPERATION)
	// --------------------------------------------------------------------------------------
	always @(posedge rd_clk_i) begin
		if (rd_en_i & !empty_o) begin
			rd_data_o <= memory[rd_ptr[ADDR_WIDTH-1:0]];
		end
	end

endmodule

day_017/multiBitCDC/multiBitCDCTB.v
`timescale 1ns / 1ps

module multi_bit_cdc_tb;

	parameter WIDTH = 32;
	parameter DEPTH = 16;

	reg  wr_clk_i;
	reg  rd_clk_i;
	reg  wr_rst_n_i;
	reg  rd_rst_n_i;
	reg  wr_en_i;
	reg  rd_en_i;
	reg [WIDTH-1:0] wr_data_i;

	wire full_o;
	wire empty_o;
	wire [WIDTH-1:0] rd_data_o;

	integer i;
	integer j;

	multi_bit_cdc #(
		.WIDTH(WIDTH), .DEPTH(DEPTH)
	) uut (
		.wr_clk_i(wr_clk_i), 	 .rd_clk_i(rd_clk_i),
		.wr_rst_n_i(wr_rst_n_i), .rd_rst_n_i(rd_rst_n_i),
		.wr_en_i(wr_en_i), 	 .wr_data_i(wr_data_i),
		.full_o(full_o), 	 .rd_en_i(rd_en_i),
		.rd_data_o(rd_data_o), 	 .empty_o(empty_o)
	);

	initial begin
		wr_clk_i = 0;
		forever #1 wr_clk_i = ~wr_clk_i;
	end

	initial begin
		rd_clk_i = 0;
		forever #1.5 rd_clk_i = ~rd_clk_i;
	end

	initial begin
		$dumpfile ("multiBitCDCTB.vcd");
		$dumpvars (0, multi_bit_cdc_tb);

		$display ("\nMULTI BIT CDC (OPEN LOOP CONFIG)\n");
		$display (" wr_rst_n | rd_rst_n | wr_en | rd_en | empty | full | wr_data  | rd_data ");
		$display ("----------|----------|-------|-------|-------|------|----------|----------");
		$monitor ("     %b    |     %b    |   %b   |   %b   |   %b   |   %b  | %8h | %8h ", wr_rst_n_i, rd_rst_n_i, wr_en_i, rd_en_i, empty_o, full_o, wr_data_i, rd_data_o);

		wr_rst_n_i = 1'b0;
		rd_rst_n_i = 1'b0;
		wr_en_i    = 1'b0;
		rd_en_i    = 1'b0;
		wr_data_i  = 'b0;

		@(negedge wr_clk_i);
		wr_rst_n_i = 1'b1;
		rd_rst_n_i = 1'b1;

		// -----------------------------------------------------------------------------
		// seperating clock domains to avoid any irl hardware violations
		// -----------------------------------------------------------------------------
		fork
			// - - - - - - - - - - - - - - - - - - - - - - - - - - - - - - - - - - -
			// wr_clk_i controlled domain
			// - - - - - - - - - - - - - - - - - - - - - - - - - - - - - - - - - - -
			begin
				@(negedge wr_clk_i);
				wr_en_i = 1'b0;

				for (i=0; i<5; i++) begin
					@(posedge wr_clk_i);
					for (j=0; j<4; j++) begin
						repeat(2) @(negedge wr_clk_i);
						wr_data_i = $urandom_range (0, 2**(WIDTH-1)-1);

						if (j==0 & i==1) wr_en_i = 1'b1;
						if (j==3 & i==2) wr_en_i = 1'b0;
						if (j==2 & i==3) wr_en_i = 1'b1;
					end
				end
			end
	
			// - - - - - - - - - - - - - - - - - - - - - - - - - - - - - - - - - - -
			// rd_clk_i controlled domain
			// - - - - - - - - - - - - - - - - - - - - - - - - - - - - - - - - - - -
			begin
				repeat(4) @(negedge rd_clk_i);
				rd_en_i = 1'b1;

				repeat(30) @(negedge rd_clk_i);
				wr_en_i = 1'b0;

				repeat(5) @(negedge rd_clk_i);
				rd_en_i = 1'b0;
			end
		join	// this joined these 2 things such that they happen simultaneously

		$display ("\nSIM FIN");
		$finish;
	end

endmodule

day_017/multiBitCDC/multiBitCDCTB.vcd
$date
	Sun Jul 12 00:50:11 2026
$end
$version
	Icarus Verilog
$end
$timescale
	1ps
$end
$scope module multi_bit_cdc_tb $end
$var wire 32 ! rd_data_o [31:0] $end
$var wire 1 " full_o $end
$var wire 1 # empty_o $end
$var parameter 32 $ DEPTH $end
$var parameter 32 % WIDTH $end
$var reg 1 & rd_clk_i $end
$var reg 1 ' rd_en_i $end
$var reg 1 ( rd_rst_n_i $end
$var reg 1 ) wr_clk_i $end
$var reg 32 * wr_data_i [31:0] $end
$var reg 1 + wr_en_i $end
$var reg 1 , wr_rst_n_i $end
$var integer 32 - i [31:0] $end
$var integer 32 . j [31:0] $end
$scope module uut $end
$var wire 1 & rd_clk_i $end
$var wire 1 ' rd_en_i $end
$var wire 1 ( rd_rst_n_i $end
$var wire 1 ) wr_clk_i $end
$var wire 32 / wr_data_i [31:0] $end
$var wire 1 + wr_en_i $end
$var wire 1 , wr_rst_n_i $end
$var wire 5 0 wr_ptr [4:0] $end
$var wire 5 1 rd_ptr [4:0] $end
$var wire 5 2 g_wr_ptr [4:0] $end
$var wire 5 3 g_rd_ptr [4:0] $end
$var wire 1 " full_o $end
$var wire 1 # empty_o $end
$var parameter 32 4 ADDR_WIDTH $end
$var parameter 32 5 DEPTH $end
$var parameter 32 6 WIDTH $end
$var reg 5 7 g_rd_ptr_q [4:0] $end
$var reg 5 8 g_rd_ptr_sync [4:0] $end
$var reg 5 9 g_wr_ptr_q [4:0] $end
$var reg 5 : g_wr_ptr_sync [4:0] $end
$var reg 32 ; rd_data_o [31:0] $end
$scope module rd_ptr_inst $end
$var wire 1 & clk $end
$var wire 5 < g_rd_ptr [4:0] $end
$var wire 5 = g_wr_ptr_sync [4:0] $end
$var wire 1 ' rd_en $end
$var wire 1 ( rst_n $end
$var wire 1 # empty $end
$var parameter 32 > ADDR_WIDTH $end
$var reg 5 ? rd_ptr [4:0] $end
$upscope $end
$scope module wr_ptr_inst $end
$var wire 1 ) clk $end
$var wire 1 " full $end
$var wire 5 @ g_rd_ptr_sync [4:0] $end
$var wire 5 A g_wr_ptr [4:0] $end
$var wire 1 , rst_n $end
$var wire 1 + wr_en $end
$var parameter 32 B ADDR_WIDTH $end
$var reg 5 C wr_ptr [4:0] $end
$upscope $end
$upscope $end
$upscope $end
$enddefinitions $end
$comment Show the parameter values. $end
$dumpall
b100 B
b100 >
b100000 6
b10000 5
b100 4
b100000 %
b10000 $
$end
#0
$dumpvars
b0 C
b0 A
b0 @
b0 ?
b0 =
b0 <
bx ;
b0 :
b0 9
b0 8
b0 7
b0 3
b0 2
b0 1
b0 0
b0 /
bx .
bx -
0,
0+
b0 *
0)
0(
0'
0&
1#
0"
bx !
$end
#1000
1)
#1500
1&
#2000
1(
1,
0)
#3000
1)
0&
#4000
b0 -
0)
#4500
1&
#5000
b0 .
1)
#6000
0)
0&
#7000
1)
#7500
1&
#8000
b1 .
b1001001000010101001101010010010 *
b1001001000010101001101010010010 /
0)
#9000
1)
0&
#10000
0)
#10500
1&
#11000
1)
#12000
b10 .
b100000010001001010111101000000 *
b100000010001001010111101000000 /
1'
0)
0&
#13000
1)
#13500
1&
#14000
0)
#15000
1)
0&
#16000
b11 .
b10010000100110101100000100 *
b10010000100110101100000100 /
0)
#16500
1&
#17000
1)
#18000
0)
0&
#19000
1)
#19500
1&
#20000
b1 -
b100 .
b11000111110000010101100110001 *
b11000111110000010101100110001 /
0)
#21000
b0 .
1)
0&
#22000
0)
#22500
1&
#23000
1)
#24000
b1 .
1+
b1000011010111001011110110000110 *
b1000011010111001011110110000110 /
0)
0&
#25000
b1 2
b1 A
b1 0
b1 C
1)
#25500
b1 9
1&
#26000
0)
#27000
b11 2
b11 A
b10 0
b10 C
1)
0&
#28000
b10 .
b1100011011011111100110011000110 *
b1100011011011111100110011000110 /
0)
#28500
0#
b1 :
b1 =
b11 9
1&
#29000
b10 2
b10 A
b11 0
b11 C
1)
#30000
0)
0&
#31000
b110 2
b110 A
b100 0
b100 C
1)
#31500
b1 3
b1 <
b11 :
b11 =
b110 9
b1 1
b1 ?
b1000011010111001011110110000110 !
b1000011010111001011110110000110 ;
1&
#32000
b11 .
b11001011000010100001000110010 *
b11001011000010100001000110010 /
0)
#33000
b111 2
b111 A
b1 7
b101 0
b101 C
1)
0&
#34000
0)
#34500
b11 3
b11 <
b10 1
b10 ?
b110 :
b110 =
b111 9
1&
#35000
b101 2
b101 A
b110 0
b110 C
b1 8
b1 @
b11 7
1)
#36000
b10 -
b100 .
b100100110111010100100001001 *
b100100110111010100100001001 /
0)
0&
#37000
b100 2
b100 A
b11 8
b11 @
b111 0
b111 C
b0 .
1)
#37500
b10 3
b10 <
b111 :
b111 =
b100 9
b11 1
b11 ?
b1100011011011111100110011000110 !
b1100011011011111100110011000110 ;
1&
#38000
0)
#39000
b1100 2
b1100 A
b1000 0
b1000 C
b10 7
1)
0&
#40000
b1 .
b1000000011110011111000110000000 *
b1000000011110011111000110000000 /
0)
#40500
b110 3
b110 <
b100 1
b100 ?
b100 :
b100 =
b1100 9
1&
#41000
b1101 2
b1101 A
b10 8
b10 @
b110 7
b1001 0
b1001 C
1)
#42000
0)
0&
#43000
b1111 2
b1111 A
b1010 0
b1010 C
b110 8
b110 @
1)
#43500
b111 3
b111 <
b1100 :
b1100 =
b1111 9
b101 1
b101 ?
b11001011000010100001000110010 !
b11001011000010100001000110010 ;
1&
#44000
b10 .
b1000011011010111110011010000110 *
b1000011011010111110011010000110 /
0)
#45000
b1110 2
b1110 A
b111 7
b1011 0
b1011 C
1)
0&
#46000
0)
#46500
b101 3
b101 <
b110 1
b110 ?
b1111 :
b1111 =
b1110 9
1&
#47000
b1010 2
b1010 A
b1100 0
b1100 C
b111 8
b111 @
b101 7
1)
#48000
b11 .
b1011101100100011111100010111011 *
b1011101100100011111100010111011 /
0)
0&
#49000
b1011 2
b1011 A
b101 8
b101 @
b1101 0
b1101 C
1)
#49500
b100 3
b100 <
b1110 :
b1110 =
b1011 9
b111 1
b111 ?
b100100110111010100100001001 !
b100100110111010100100001001 ;
1&
#50000
0)
#51000
b1001 2
b1001 A
b1110 0
b1110 C
b100 7
1)
0&
#52000
b11 -
b100 .
0+
b1001111010001101110011010011110 *
b1001111010001101110011010011110 /
0)
#52500
0#
b1100 3
b1100 <
b1000 1
b1000 ?
b1011 :
b1011 =
b1001 9
1&
#53000
b100 8
b100 @
b1100 7
b0 .
1)
#54000
0)
0&
#55000
b1100 8
b1100 @
1)
#55500
b1101 3
b1101 <
b1001 :
b1001 =
b1001 1
b1001 ?
b1000000011110011111000110000000 !
b1000000011110011111000110000000 ;
1&
#56000
b1 .
b1111011011010100010101111110110 *
b1111011011010100010101111110110 /
0)
#57000
b1101 7
1)
0&
#58000
0)
#58500
b1111 3
b1111 <
b1010 1
b1010 ?
1&
#59000
b1101 8
b1101 @
b1111 7
1)
#60000
b10 .
b1100011000101101111101111000110 *
b1100011000101101111101111000110 /
0)
0&
#61000
b1111 8
b1111 @
1)
#61500
b1110 3
b1110 <
b1011 1
b1011 ?
b1000011011010111110011010000110 !
b1000011011010111110011010000110 ;
1&
#62000
0)
#63000
b1110 7
1)
0&
#64000
b11 .
1+
b1111110011111101111010011111100 *
b1111110011111101111010011111100 /
0)
#64500
0#
b1010 3
b1010 <
b1100 1
b1100 ?
1&
#65000
b1000 2
b1000 A
b1110 8
b1110 @
b1010 7
b1111 0
b1111 C
1)
#66000
0)
0&
#67000
b11000 2
b11000 A
b10000 0
b10000 C
b1010 8
b1010 @
1)
#67500
b1011 3
b1011 <
b11000 9
b1101 1
b1101 ?
b1011101100100011111100010111011 !
b1011101100100011111100010111011 ;
1&
#68000
b100 -
b100 .
b110001100110111001001001100011 *
b110001100110111001001001100011 /
0)
#69000
b11001 2
b11001 A
b1011 7
b10001 0
b10001 C
b0 .
1)
0&
#70000
0)
#70500
b1001 3
b1001 <
b1110 1
b1110 ?
b11000 :
b11000 =
b11001 9
1&
#71000
b11011 2
b11011 A
b10010 0
b10010 C
b1011 8
b1011 @
b1001 7
1)
#72000
b1 .
b110001011110111100001001100010 *
b110001011110111100001001100010 /
0)
0&
#73000
b11010 2
b11010 A
b1001 8
b1001 @
b10011 0
b10011 C
1)
#73500
b1000 3
b1000 <
b11001 :
b11001 =
b11010 9
b1111 1
b1111 ?
b1111110011111101111010011111100 !
b1111110011111101111010011111100 ;
1&
#74000
0)
#75000
b11110 2
b11110 A
b10100 0
b10100 C
b1000 7
1)
0&
#76000
b10 .
b101010100010011110100101010101 *
b101010100010011110100101010101 /
0)
#76500
b11000 3
b11000 <
b10000 1
b10000 ?
b11010 :
b11010 =
b11110 9
1&
#77000
b11111 2
b11111 A
b1000 8
b1000 @
b11000 7
b10101 0
b10101 C
1)
#78000
0)
0&
#79000
b11101 2
b11101 A
b10110 0
b10110 C
b11000 8
b11000 @
1)
#79500
b11001 3
b11001 <
b11110 :
b11110 =
b11101 9
b10001 1
b10001 ?
b110001100110111001001001100011 !
b110001100110111001001001100011 ;
1&
#80000
b11 .
b1111001010101111111101111110010 *
b1111001010101111111101111110010 /
0)
#81000
b11100 2
b11100 A
b11001 7
b10111 0
b10111 C
1)
0&
#82000
0)
#82500
b11011 3
b11011 <
b10010 1
b10010 ?
b11101 :
b11101 =
b11100 9
1&
#83000
b10100 2
b10100 A
b11000 0
b11000 C
b11001 8
b11001 @
b11011 7
1)
#84000
b101 -
b100 .
b11101111010010011100100111011 *
b11101111010010011100100111011 /
0)
0&
#85000
b10101 2
b10101 A
b11011 8
b11011 @
b11001 0
b11001 C
1)
#85500
b11010 3
b11010 <
b11100 :
b11100 =
b10101 9
b10011 1
b10011 ?
b110001011110111100001001100010 !
b110001011110111100001001100010 ;
1&
#86000
0)
#87000
b10111 2
b10111 A
b11010 0
b11010 C
b11010 7
1)
0&
#88000
0)
#88500
b11110 3
b11110 <
b10100 1
b10100 ?
b10101 :
b10101 =
b10111 9
1&
#89000
b10110 2
b10110 A
b11010 8
b11010 @
b11110 7
b11011 0
b11011 C
1)
#90000
0)
0&
#91000
b10010 2
b10010 A
b11100 0
b11100 C
b11110 8
b11110 @
1)
#91500
b11111 3
b11111 <
b10111 :
b10111 =
b10010 9
b10101 1
b10101 ?
b101010100010011110100101010101 !
b101010100010011110100101010101 ;
1&
#92000
0)
#93000
b10011 2
b10011 A
b11111 7
b11101 0
b11101 C
1)
0&
#94000
0)
#94500
b11101 3
b11101 <
b10110 1
b10110 ?
b10010 :
b10010 =
b10011 9
1&
#95000
b10001 2
b10001 A
b11110 0
b11110 C
b11111 8
b11111 @
b11101 7
1)
#96000
0)
0&
#97000
b10000 2
b10000 A
b11101 8
b11101 @
b11111 0
b11111 C
1)
#97500
b11100 3
b11100 <
b10011 :
b10011 =
b10000 9
b10111 1
b10111 ?
b1111001010101111111101111110010 !
b1111001010101111111101111110010 ;
1&
#98000
0)
#99000
b0 2
b0 A
b0 0
b0 C
b11100 7
1)
0&
#100000
0)
#100500
b10100 3
b10100 <
b11000 1
b11000 ?
b10000 :
b10000 =
b0 9
1&
#101000
b1 2
b1 A
b11100 8
b11100 @
b10100 7
b1 0
b1 C
1)
#102000
0+
0)
0&
#103000
b10100 8
b10100 @
1)
#103500
b10101 3
b10101 <
b0 :
b0 =
b1 9
b11001 1
b11001 ?
b11101111010010011100100111011 !
b11101111010010011100100111011 ;
1&
#104000
0)
#105000
b10101 7
1)
0&
#106000
0)
#106500
b10111 3
b10111 <
b11010 1
b11010 ?
b1 :
b1 =
1&
#107000
b10101 8
b10101 @
b10111 7
1)
#108000
0)
0&
#109000
b10111 8
b10111 @
1)
#109500
b10110 3
b10110 <
b11011 1
b11011 ?
1&
#110000
0)
#111000
b10110 7
1)
0&
#112000
0)
#112500
b10010 3
b10010 <
b11100 1
b11100 ?
1&
#113000
b10110 8
b10110 @
b10010 7
1)
#114000
0)
0&
#115000
b10010 8
b10010 @
1)
#115500
b10011 3
b10011 <
b11101 1
b11101 ?
1&
#116000
0)
#117000
b10011 7
0'
1)
0&
