day_017/multiBitCDC/rd_ptr.v
`timescale 1ns / 1ps

module RD_PTR #(
	parameter ADDR_WIDTH = 4
) (
	input wire 		   clk,
	input wire 		   rst_n,
	input wire 		   rd_en,
	input wire [ADDR_WIDTH:0] g_wr_ptr_sync,

	output reg  [ADDR_WIDTH:0] rd_ptr,
	output wire [ADDR_WIDTH:0] g_rd_ptr,
	output wire 		   empty
);

	assign g_rd_ptr = (rd_ptr >> 1) ^ rd_ptr;

	always @(posedge clk or negedge rst_n) begin
		if (!rst_n) begin
			rd_ptr <= {(ADDR_WIDTH+1){1'b0}};
		end
		else if (rd_en & !empty) begin
			rd_ptr <= rd_ptr + 1'b1;
		end
	end

	assign empty = (g_rd_ptr == g_wr_ptr_sync);

endmodule

day_017/multiBitCDC/wr_ptr.v
`timescale 1ns / 1ps

module WR_PTR #(
	parameter ADDR_WIDTH = 4
) (
	input  wire 		   clk,
	input  wire 		   rst_n,
	input  wire 		   wr_en,
	input  wire [ADDR_WIDTH:0] g_rd_ptr_sync,

	output reg  [ADDR_WIDTH:0] wr_ptr,
	output wire [ADDR_WIDTH:0] g_wr_ptr,
	output wire 		   full
);

	assign g_wr_ptr = (wr_ptr >> 1) ^ wr_ptr;

	always @(posedge clk or negedge rst_n) begin
		if (!rst_n) begin
			wr_ptr   <= {(ADDR_WIDTH+1){1'b0}};
		end
		else if (wr_en & !full) begin
			wr_ptr <= wr_ptr + 1'b1;
		end
	end

	assign full = (g_wr_ptr[ADDR_WIDTH:ADDR_WIDTH-1] == ~g_rd_ptr_sync[ADDR_WIDTH:ADDR_WIDTH-1]) &
		      (g_wr_ptr[ADDR_WIDTH-2:0] == g_rd_ptr_sync[ADDR_WIDTH-2:0]);

endmodule

day_017/multiBitCDC/multiBitCDC.v
`timescale 1ns / 1ps

module multi_bit_cdc #(
	parameter WIDTH = 32,
	parameter DEPTH = 16
) (
	// ------------------------------
	// clocks and reset
	input wire wr_clk_i,
	input wire rd_clk_i,
	input wire wr_rst_n_i,
	input wire rd_rst_n_i,
	// ------------------------------
	// write
	input wire 	       wr_en_i,
	input wire [WIDTH-1:0] wr_data_i,
	output wire 	       full_o,
	// ------------------------------
	// read
	input wire 	       rd_en_i,
	output reg [WIDTH-1:0] rd_data_o,
	output wire	       empty_o
);

	// ------------------------------------------------------
	// for the pointers to be able to address the fifo memory
	localparam ADDR_WIDTH = $clog2 (DEPTH);

	// --------------------------------------------------------------------------------------
	// read and write pointers: binary, gray and synchronized
	// the pointers are assigned an extra bit to allow for smoother
	// calculation of which operation happened last (write, read)
	wire [ADDR_WIDTH:0] wr_ptr;		// binary write ptr
	wire [ADDR_WIDTH:0] rd_ptr;		// binary read ptr
	wire [ADDR_WIDTH:0] g_wr_ptr;		// gray write ptr
	wire [ADDR_WIDTH:0] g_rd_ptr;		// gray read ptr
	reg  [ADDR_WIDTH:0] g_wr_ptr_sync;	// synchronized gray write ptr for cdc - FLOP O/P
	reg  [ADDR_WIDTH:0] g_rd_ptr_sync;	// synchronized gray read ptr for cdc - FLOP O/P

	// ----------------------------
	// memory
	reg [WIDTH-1:0] memory [0:DEPTH-1];

	// ---------------------------------------------------------------------------
	// registers acting as o/p of flops (for CDC)
	reg [ADDR_WIDTH:0] g_wr_ptr_q;		// first flop's output for write
	reg [ADDR_WIDTH:0] g_rd_ptr_q;		// first flop's output for read
	// `g_wr_ptr_q` will be the i/p to 2nd flop, whose o/p will be `g_wr_ptr_sync`
	// `g_rd_ptr_q` will be the i/p to 2nd flop, whose o/p will be `g_rd_ptr_sync`

	// --------------------------------------------------------------------------------------
	// write pointer function instance
	// --------------------------------------------------------------------------------------
	WR_PTR wr_ptr_inst (
		.clk(wr_clk_i), .rst_n(wr_rst_n_i),
		.wr_en(wr_en_i), .wr_ptr(wr_ptr),
		.g_wr_ptr(g_wr_ptr), .g_rd_ptr_sync(g_rd_ptr_sync),
		.full(full_o)
	);

	// --------------------------------------------------------------------------------------
	// read pointer function instance
	// --------------------------------------------------------------------------------------
	RD_PTR rd_ptr_inst (
		.clk(rd_clk_i), .rst_n(rd_rst_n_i),
		.rd_en(rd_en_i), .rd_ptr(rd_ptr),
		.g_rd_ptr(g_rd_ptr), .g_wr_ptr_sync(g_wr_ptr_sync),
		.empty(empty_o)
	);

	// --------------------------------------------------------------------------------------
	// dual flops using `always` block
	// these will be used to allow cdc of the gray-coded pointer values
	// input to flop    -> gray-coded pointer values
	// output from flop -> gray-coded synchronized pointer values
	// - - - - - - - - - - - - - - - - - - - - - - - - - - - - - - - - - - - - - - - - - - - 
	// write flop
	// - - - - - - - - - - - - - - - - - - - - - - - - - - - - - - - - - - - - - - - - - - - 
	always @(posedge wr_clk_i or negedge wr_rst_n_i) begin
		if (!wr_rst_n_i) begin
			g_rd_ptr_q    <= {(ADDR_WIDTH+1){1'b0}};
			g_rd_ptr_sync <= {(ADDR_WIDTH+1){1'b0}};
		end
		else begin
			g_rd_ptr_q    <= g_rd_ptr;
			g_rd_ptr_sync <= g_rd_ptr_q;
		end
	end

	// - - - - - - - - - - - - - - - - - - - - - - - - - - - - - - - - - - - - - - - - - - - 
	//read flop
	// - - - - - - - - - - - - - - - - - - - - - - - - - - - - - - - - - - - - - - - - - - - 
	always @(posedge rd_clk_i or negedge rd_rst_n_i) begin
		if (!rd_rst_n_i) begin
			g_wr_ptr_q    <= {(ADDR_WIDTH+1){1'b0}};
			g_wr_ptr_sync <= {(ADDR_WIDTH+1){1'b0}};
		end
		else begin			
			g_wr_ptr_q    <= g_wr_ptr;
			g_wr_ptr_sync <= g_wr_ptr_q;
		end
	end

	// --------------------------------------------------------------------------------------
	// storing data values inside of FIFO (WRITE OPERATION)
	// --------------------------------------------------------------------------------------
	always @(posedge wr_clk_i) begin
		if (wr_en_i & !full_o) begin
			memory[wr_ptr[ADDR_WIDTH-1:0]] <= wr_data_i;
		end
	end

	// --------------------------------------------------------------------------------------
	// reading data values from FIFO (READ OPERATION)
	// --------------------------------------------------------------------------------------
	always @(posedge rd_clk_i) begin
		if (rd_en_i & !empty_o) begin
			rd_data_o <= memory[rd_ptr[ADDR_WIDTH-1:0]];
		end
	end

endmodule

day_017/multiBitCDC/multiBitCDCTB.v
`timescale 1ns / 1ps

module multi_bit_cdc_tb;

	parameter WIDTH = 32;
	parameter DEPTH = 16;

	reg  wr_clk_i;
	reg  rd_clk_i;
	reg  wr_rst_n_i;
	reg  rd_rst_n_i;
	reg  wr_en_i;
	reg  rd_en_i;
	reg [WIDTH-1:0] wr_data_i;

	wire full_o;
	wire empty_o;
	wire [WIDTH-1:0] rd_data_o;

	integer i;
	integer j;

	multi_bit_cdc #(
		.WIDTH(WIDTH), .DEPTH(DEPTH)
	) uut (
		.wr_clk_i(wr_clk_i), 	 .rd_clk_i(rd_clk_i),
		.wr_rst_n_i(wr_rst_n_i), .rd_rst_n_i(rd_rst_n_i),
		.wr_en_i(wr_en_i), 	 .wr_data_i(wr_data_i),
		.full_o(full_o), 	 .rd_en_i(rd_en_i),
		.rd_data_o(rd_data_o), 	 .empty_o(empty_o)
	);

	initial begin
		wr_clk_i = 0;
		forever #1 wr_clk_i = ~wr_clk_i;
	end

	initial begin
		rd_clk_i = 0;
		forever #1.5 rd_clk_i = ~rd_clk_i;
	end

	initial begin
		$dumpfile ("multiBitCDCTB.vcd");
		$dumpvars (0, multi_bit_cdc_tb);

		$display ("\nMULTI BIT CDC (OPEN LOOP CONFIG)\n");
		$display (" wr_rst_n | rd_rst_n | wr_en | rd_en | empty | full | wr_data | rd_data ");
		$display ("----------|----------|-------|-------|-------|------|---------|---------");
		$monitor ("     %b     |     %b     |   %b   |   %b   |   %b   |   %b   | %0h | %0h ", wr_rst_n_i, rd_rst_n_i, wr_en_i, rd_en_i, empty_o, full_o, wr_data_i, rd_data_o);

		wr_rst_n_i = 1'b0;
		rd_rst_n_i = 1'b0;
		wr_en_i    = 1'b0;
		rd_en_i    = 1'b0;
		wr_data_i  = 'b0;

		@(negedge wr_clk_i);
		wr_rst_n_i = 1'b1;
		rd_rst_n_i = 1'b1;
		wr_en_i    = 1'b1;

		for (i=0; i<5; i++) begin
			@(posedge wr_clk_i);
			for (j=0; j<4; j++) begin
				repeat(2) @(negedge wr_clk_i);
				wr_data_i = $urandom_range (0, 2**(WIDTH-1)-1);

				if (j==0 & i==2) rd_en_i = 1'b1;
				if (j==1 & i==2) rd_en_i = 1'b0;
				if (j==2 & i==0) rd_en_i = 1'b1;
				if (j==3 & i==0) wr_en_i = 1'b0;
				if (j==3 & i==4) wr_en_i = 1'b1;
			end
	
			repeat(4) @(negedge wr_clk_i);
		end

		$display ("\nSIM FIN");
		$finish;
	end

endmodule

day_017/multiBitCDC/multiBitCDCTB.vcd
$date
	Sat Jul 11 23:54:20 2026
$end
$version
	Icarus Verilog
$end
$timescale
	1ps
$end
$scope module multi_bit_cdc_tb $end
$var wire 32 ! rd_data_o [31:0] $end
$var wire 1 " full_o $end
$var wire 1 # empty_o $end
$var parameter 32 $ DEPTH $end
$var parameter 32 % WIDTH $end
$var reg 1 & rd_clk_i $end
$var reg 1 ' rd_en_i $end
$var reg 1 ( rd_rst_n_i $end
$var reg 1 ) wr_clk_i $end
$var reg 32 * wr_data_i [31:0] $end
$var reg 1 + wr_en_i $end
$var reg 1 , wr_rst_n_i $end
$var integer 32 - i [31:0] $end
$var integer 32 . j [31:0] $end
$scope module uut $end
$var wire 1 & rd_clk_i $end
$var wire 1 ' rd_en_i $end
$var wire 1 ( rd_rst_n_i $end
$var wire 1 ) wr_clk_i $end
$var wire 32 / wr_data_i [31:0] $end
$var wire 1 + wr_en_i $end
$var wire 1 , wr_rst_n_i $end
$var wire 5 0 wr_ptr [4:0] $end
$var wire 5 1 rd_ptr [4:0] $end
$var wire 5 2 g_wr_ptr [4:0] $end
$var wire 5 3 g_rd_ptr [4:0] $end
$var wire 1 " full_o $end
$var wire 1 # empty_o $end
$var parameter 32 4 ADDR_WIDTH $end
$var parameter 32 5 DEPTH $end
$var parameter 32 6 WIDTH $end
$var reg 5 7 g_rd_ptr_q [4:0] $end
$var reg 5 8 g_rd_ptr_sync [4:0] $end
$var reg 5 9 g_wr_ptr_q [4:0] $end
$var reg 5 : g_wr_ptr_sync [4:0] $end
$var reg 32 ; rd_data_o [31:0] $end
$scope module rd_ptr_inst $end
$var wire 1 & clk $end
$var wire 5 < g_rd_ptr [4:0] $end
$var wire 5 = g_wr_ptr_sync [4:0] $end
$var wire 1 ' rd_en $end
$var wire 1 ( rst_n $end
$var wire 1 # empty $end
$var parameter 32 > ADDR_WIDTH $end
$var reg 5 ? rd_ptr [4:0] $end
$upscope $end
$scope module wr_ptr_inst $end
$var wire 1 ) clk $end
$var wire 1 " full $end
$var wire 5 @ g_rd_ptr_sync [4:0] $end
$var wire 5 A g_wr_ptr [4:0] $end
$var wire 1 , rst_n $end
$var wire 1 + wr_en $end
$var parameter 32 B ADDR_WIDTH $end
$var reg 5 C wr_ptr [4:0] $end
$upscope $end
$upscope $end
$upscope $end
$enddefinitions $end
$comment Show the parameter values. $end
$dumpall
b100 B
b100 >
b100000 6
b10000 5
b100 4
b100000 %
b10000 $
$end
#0
$dumpvars
b0 C
b0 A
b0 @
b0 ?
b0 =
b0 <
bx ;
b0 :
b0 9
b0 8
b0 7
b0 3
b0 2
b0 1
b0 0
b0 /
bx .
bx -
0,
0+
b0 *
0)
0(
0'
0&
1#
0"
bx !
$end
#1000
1)
#1500
1&
#2000
b0 -
1(
1,
0)
#3000
b0 .
1)
0&
#4000
0)
#4500
1&
#5000
1)
#6000
b1 .
b10010010000101010011010100100100 *
b10010010000101010011010100100100 /
0)
0&
#7000
1)
#7500
1&
#8000
0)
#9000
1)
0&
#10000
b10 .
b1000000100010010101111010000001 *
b1000000100010010101111010000001 /
0)
#10500
1&
#11000
1)
#12000
0)
0&
#13000
1)
#13500
1&
#14000
b11 .
1'
b100100001001101011000001001 *
b100100001001101011000001001 /
0)
#15000
1)
0&
#16000
0)
#16500
1&
#17000
1)
#18000
0)
0&
#19000
1)
#19500
1&
#20000
0)
#21000
1)
0&
#22000
b1 -
0)
#22500
1&
#23000
b0 .
1)
#24000
0)
0&
#25000
1)
#25500
1&
#26000
b1 .
b110001111100000101011001100011 *
b110001111100000101011001100011 /
0)
#27000
1)
0&
#28000
0)
#28500
1&
#29000
1)
#30000
b10 .
b10000110101110010111101100001101 *
b10000110101110010111101100001101 /
0)
0&
#31000
1)
#31500
1&
#32000
0)
#33000
1)
0&
#34000
b11 .
b11000110110111111001100110001101 *
b11000110110111111001100110001101 /
0)
#34500
1&
#35000
1)
#36000
0)
0&
#37000
1)
#37500
1&
#38000
0)
#39000
1)
0&
#40000
0)
#40500
1&
#41000
1)
#42000
b10 -
0)
0&
#43000
b0 .
1)
#43500
1&
#44000
0)
#45000
1)
0&
#46000
b1 .
b110010110000101000010001100101 *
b110010110000101000010001100101 /
0)
#46500
1&
#47000
1)
#48000
0)
0&
#49000
1)
#49500
1&
#50000
b10 .
0'
b1001001101110101001000010010 *
b1001001101110101001000010010 /
0)
#51000
1)
0&
#52000
0)
#52500
1&
#53000
1)
#54000
b11 .
b10000000111100111110001100000001 *
b10000000111100111110001100000001 /
0)
0&
#55000
1)
#55500
1&
#56000
0)
#57000
1)
0&
#58000
0)
#58500
1&
#59000
1)
#60000
0)
0&
#61000
1)
#61500
1&
#62000
b11 -
0)
