day_017/singleBitCDC/singleBitCDC.v
`timescale 1ns / 1ps

module single_bit_cdc (
	input wire clk_a,
	input wire clk_b,
	input wire rst_n,
	input wire a,
	output reg y
);

	reg a_q;
	reg b_q;

	always @(posedge clk_a or negedge rst_n) begin
		if (!rst_n) begin
			a_q <= 1'b0;
		end
		else begin
			a_q <= a;
		end
	end

	always @(posedge clk_b or negedge rst_n) begin
		if (!rst_n) begin
			b_q <= 1'b0;
			y   <= 1'b0;
		end
		else begin
			b_q <= a_q;
			y   <= b_q;
		end
	end

endmodule

day_017/singleBitCDC/singleBitCDCTB.v
`timescale 1ns / 1ps

module single_bit_cdc_tb;

	reg  clk_a;
	reg  clk_b;
	reg  rst_n;
	reg  a;
	wire y;

	integer i;

	single_bit_cdc uut (
		.clk_a(clk_a), .clk_b(clk_b),
		.rst_n(rst_n), .a(a), .y(y)
	);

	initial begin
		clk_a = 0;
		forever #1 clk_a = ~clk_a;
	end

	initial begin
		clk_b = 0;
		forever #1.5 clk_b = ~clk_b;
	end

	initial begin
		$dumpfile ("singleBitCDCTB.vcd");
		$dumpvars (0, single_bit_cdc_tb);

		$display ("\nSINGLE BIT CDC (OPEN LOOP CONFIG)\n");
		$display (" a | y ");
		$display ("---|---");
		$monitor (" %b | %b ", a, y);

		rst_n = 1'b0;
		a     = 1'bx;

		for (i=0; i<5; i++) begin
			@(negedge clk_a);
			rst_n = 1'b1;
			a     = 1'b0;
	
			@(posedge clk_a);
			repeat(2) @(negedge clk_a);
			a = 1'b1;
	
			repeat(4) @(negedge clk_a);
		end

		$display ("\nSIM FIN");
		$finish;
	end

endmodule

day_017/singleBitCDC/singleBitCDCTB.vcd
$date
	Sat Jul 11 15:49:03 2026
$end
$version
	Icarus Verilog
$end
$timescale
	1ps
$end
$scope module single_bit_cdc_tb $end
$var wire 1 ! y $end
$var reg 1 " a $end
$var reg 1 # clk_a $end
$var reg 1 $ clk_b $end
$var reg 1 % rst_n $end
$var integer 32 & i [31:0] $end
$scope module uut $end
$var wire 1 " a $end
$var wire 1 # clk_a $end
$var wire 1 $ clk_b $end
$var wire 1 % rst_n $end
$var reg 1 ' a_q $end
$var reg 1 ( b_q $end
$var reg 1 ! y $end
$upscope $end
$upscope $end
$enddefinitions $end
$comment Show the parameter values. $end
$dumpall
$end
#0
$dumpvars
0(
0'
b0 &
0%
0$
0#
x"
0!
$end
#1000
1#
#1500
1$
#2000
0"
1%
0#
#3000
1#
0$
#4000
0#
#4500
1$
#5000
1#
#6000
1"
0#
0$
#7000
1'
1#
#7500
1(
1$
#8000
0#
#9000
1#
0$
#10000
0#
#10500
1!
1$
#11000
1#
#12000
0#
0$
#13000
1#
#13500
1$
#14000
b1 &
0#
#15000
1#
0$
#16000
0"
0#
#16500
1$
#17000
0'
1#
#18000
0#
0$
#19000
1#
#19500
0(
1$
#20000
1"
0#
#21000
1'
1#
0$
#22000
0#
#22500
0!
1(
1$
#23000
1#
#24000
0#
0$
#25000
1#
#25500
1!
1$
#26000
0#
#27000
1#
0$
#28000
b10 &
0#
#28500
1$
#29000
1#
#30000
0"
0#
0$
#31000
0'
1#
#31500
0(
1$
#32000
0#
#33000
1#
0$
#34000
1"
0#
#34500
0!
1$
#35000
1'
1#
#36000
0#
0$
#37000
1#
#37500
1(
1$
#38000
0#
#39000
1#
0$
#40000
0#
#40500
1!
1$
#41000
1#
#42000
b11 &
0#
0$
#43000
1#
#43500
1$
#44000
0"
0#
#45000
0'
1#
0$
#46000
0#
#46500
0(
1$
#47000
1#
#48000
1"
0#
0$
#49000
1'
1#
#49500
0!
1(
1$
#50000
0#
#51000
1#
0$
#52000
0#
#52500
1!
1$
#53000
1#
#54000
0#
0$
#55000
1#
#55500
1$
#56000
b100 &
0#
#57000
1#
0$
#58000
0"
0#
#58500
1$
#59000
0'
1#
#60000
0#
0$
#61000
1#
#61500
0(
1$
#62000
1"
0#
#63000
1'
1#
0$
#64000
0#
#64500
0!
1(
1$
#65000
1#
#66000
0#
0$
#67000
1#
#67500
1!
1$
#68000
0#
#69000
1#
0$
#70000
b101 &
0#
