day_023/piso/pisoSerializer.v
`timescale 1ns / 1ps

module piso_serializer #(
	parameter WIDTH = 16
) (
	// -------------------------------
	// inputs
	input wire 	       clk_i,
	input wire 	       rst_n_i,
	input wire 	       wr_en_i,
	input wire [WIDTH-1:0] wr_data_i,
	// -------------------------------
	// outputs
	output reg 	       wr_valid_o,
	output wire 	       rd_data_o
);

	// -----------------------------------
	// number of bits for counter
	localparam WIDTH_BITS = $clog2(WIDTH);

	// ----------------------------
	// counter and shift register
	reg [WIDTH-1:0]      shift_reg;
	reg [WIDTH_BITS-1:0] counter;

	always @(posedge clk_i or negedge rst_n_i) begin
		// contents reset
		if (!rst_n_i) begin
			shift_reg  <= {WIDTH{1'b0}};
			wr_valid_o <= 1'b1;
			counter    <= {WIDTH_BITS{1'b0}};
		end
		else if (wr_en_i & wr_valid_o) begin
			shift_reg  <= wr_data_i;	   // inserted to shift reg in 1 clk cycle
			wr_valid_o <= 1'b0;		   // goes LOW after writing
			counter    <= {WIDTH_BITS{1'b0}};  // starts from 0
		end
		else if (!wr_valid_o) begin	// TRUE after shift reg is written to
			if (counter == WIDTH-1) begin	// TRUE when shifting last bit
				wr_valid_o <= 1'b1;		   // goes HIGH as shift reg can be written to
				counter    <= {WIDTH_BITS{1'b0}};  // resets to 0
			end
			else begin
				shift_reg  <= {shift_reg[WIDTH-2:0], 1'b0};
				counter    <= counter + 1'b1;
			end
		end
	end

	assign rd_data_o = shift_reg[WIDTH-1];

endmodule

day_023/piso/pisoSerializerTB.v
`timescale 1ns / 1ps

module piso_serializer_tb;

	parameter WIDTH = 16;

	reg  		 clk_i;
	reg  		 rst_n_i;
	reg  		 wr_en_i;
	reg  [WIDTH-1:0] wr_data_i;

	wire 		 wr_valid_o;
	wire		 rd_data_o;

	integer i;

	piso_serializer #(
		.WIDTH(WIDTH)
	) uut (
		.clk_i(clk_i),
		.rst_n_i(rst_n_i),
		.wr_en_i(wr_en_i),
		.wr_data_i(wr_data_i),
		.wr_valid_o(wr_valid_o),
		.rd_data_o(rd_data_o)
	);

	initial begin
		clk_i = 0;
	end

	always #1 clk_i = ~clk_i;

	initial begin
		$dumpfile ("pisoSerializerTB.vcd");
		$dumpvars (0, piso_serializer_tb);

		$display ("\nPISO: SERIALIZER\n");
		$display (" rst_n_i | wr_en_i |   wr_data_i   | wr_valid_o | rd_data_o ");
		$display ("---------|---------|-----------|------------|-----------");
		$monitor ("    %b    |    %b    | %h |     %b     |     %b   ", rst_n_i, wr_en_i, wr_data_i, wr_valid_o, rd_data_o);

		rst_n_i = 1'b0;
		wr_data_i = {WIDTH{1'b0}};
		wr_en_i   = 1'b0;

		@(posedge clk_i);
		@(negedge clk_i);
		rst_n_i   = 1'b1;

		for (i=0; i<2; i++) begin
			@(negedge clk_i);
			wr_en_i   = 1'b1;
			wr_data_i = $urandom_range (0, 2**(WIDTH-1)-1);
			repeat(WIDTH) @(negedge clk_i);
		end

		@(posedge clk_i);
		#1;

		$display ("\nSIM FIN");
		$finish;
	end

endmodule

day_023/piso/pisoSerializerTB.vcd
$date
	Sat Jul 18 00:51:38 2026
$end
$version
	Icarus Verilog
$end
$timescale
	1ps
$end
$scope module piso_serializer_tb $end
$var wire 1 ! wr_valid_o $end
$var wire 1 " rd_data_o $end
$var parameter 32 # WIDTH $end
$var reg 1 $ clk_i $end
$var reg 1 % rst_n_i $end
$var reg 16 & wr_data_i [15:0] $end
$var reg 1 ' wr_en_i $end
$var integer 32 ( i [31:0] $end
$scope module uut $end
$var wire 1 $ clk_i $end
$var wire 1 % rst_n_i $end
$var wire 16 ) wr_data_i [15:0] $end
$var wire 1 ' wr_en_i $end
$var wire 1 " rd_data_o $end
$var parameter 32 * WIDTH $end
$var parameter 32 + WIDTH_BITS $end
$var reg 4 , counter [3:0] $end
$var reg 16 - shift_reg [15:0] $end
$var reg 1 ! wr_valid_o $end
$upscope $end
$upscope $end
$enddefinitions $end
$comment Show the parameter values. $end
$dumpall
b100 +
b10000 *
b10000 #
$end
#0
$dumpvars
b0 -
b0 ,
b0 )
bx (
0'
b0 &
0%
0$
0"
1!
$end
#1000
1$
#2000
b0 (
1%
0$
#3000
1$
#4000
b100100100001010 &
b100100100001010 )
1'
0$
#5000
0!
b100100100001010 -
1$
#6000
0$
#7000
1"
b1 ,
b1001001000010100 -
1$
#8000
0$
#9000
0"
b10 ,
b10010000101000 -
1$
#10000
0$
#11000
b11 ,
b100100001010000 -
1$
#12000
0$
#13000
1"
b100 ,
b1001000010100000 -
1$
#14000
0$
#15000
0"
b101 ,
b10000101000000 -
1$
#16000
0$
#17000
b110 ,
b100001010000000 -
1$
#18000
0$
#19000
1"
b111 ,
b1000010100000000 -
1$
#20000
0$
#21000
0"
b1000 ,
b101000000000 -
1$
#22000
0$
#23000
b1001 ,
b1010000000000 -
1$
#24000
0$
#25000
b1010 ,
b10100000000000 -
1$
#26000
0$
#27000
b1011 ,
b101000000000000 -
1$
#28000
0$
#29000
1"
b1100 ,
b1010000000000000 -
1$
#30000
0$
#31000
0"
b1101 ,
b100000000000000 -
1$
#32000
0$
#33000
1"
b1110 ,
b1000000000000000 -
1$
#34000
0$
#35000
0"
b1111 ,
b0 -
1$
#36000
b1 (
0$
#37000
b0 ,
1!
1$
#38000
b10000001000100 &
b10000001000100 )
0$
#39000
0!
b10000001000100 -
1$
#40000
0$
#41000
b1 ,
b100000010001000 -
1$
#42000
0$
#43000
1"
b10 ,
b1000000100010000 -
1$
#44000
0$
#45000
0"
b11 ,
b1000100000 -
1$
#46000
0$
#47000
b100 ,
b10001000000 -
1$
#48000
0$
#49000
b101 ,
b100010000000 -
1$
#50000
0$
#51000
b110 ,
b1000100000000 -
1$
#52000
0$
#53000
b111 ,
b10001000000000 -
1$
#54000
0$
#55000
b1000 ,
b100010000000000 -
1$
#56000
0$
#57000
1"
b1001 ,
b1000100000000000 -
1$
#58000
0$
#59000
0"
b1010 ,
b1000000000000 -
1$
#60000
0$
#61000
b1011 ,
b10000000000000 -
1$
#62000
0$
#63000
b1100 ,
b100000000000000 -
1$
#64000
0$
#65000
1"
b1101 ,
b1000000000000000 -
1$
#66000
0$
#67000
0"
b1110 ,
b0 -
1$
#68000
0$
#69000
b1111 ,
1$
#70000
b10 (
0$
#71000
b0 ,
1!
1$
