day_013/srLatch/srLatch.v
`timescale 1ns / 1ps

module sr_latch (
	input wire s,
	input wire r,
	output reg q,
	output reg q_bar
);

	always @(*) begin
		case ({s,r})
			2'b00 : begin
				q = q;
				q_bar = q_bar;
			end
			
			2'b01 : begin
				q = 1'b0;
				q_bar = 1'b1;
			end

			2'b10 : begin
				q = 1'b1;
				q_bar = 1'b0;
			end

			2'b11 : begin
				q = 1'b0;
				q_bar = 1'b0;
			end

			default : begin
				q = 1'bx;
				q_bar = 1'bx;
			end
		endcase
	end

endmodule

day_013/srLatch/srLatchTB.v
`timescale 1ns / 1ps

module sr_latch_tb;

	reg  s;
	reg  r;
	wire q;
	wire q_bar;

	integer i;

	sr_latch uut (.s(s), .r(r), .q(q), .q_bar(q_bar));

	initial begin
		$timeformat (-9, 0, "", 5);

		#10;

		s = 1'b0;
		r = 1'b0;

		$dumpfile ("srLatchTB.vcd");
		$dumpvars (1, uut);

		$display ("\nSR LATCH\n");
		$display (" Time | s | r | q | q_bar");
		$display ("------|---|---|---|------");
		$monitor ("  %0t  | %b | %b | %b |  %b ", $time, s, r, q, q_bar);

		// looped twice to show output of 
		// first case when {q,q_bar} =/= 2'bxx
		for (i=0; i<2; i++) begin
			s=1'b0; r=1'b0; #10;
			s=1'b0; r=1'b1; #10;
			s=1'b1; r=1'b0; #10;
			s=1'b1; r=1'b1; #10;
		end

		#1;

		$display ("\nSIM FIN");
		$finish;
	end

endmodule

day_013/srLatch/srLatchTB.vcd
$date
	Sun Jul  5 17:13:35 2026
$end
$version
	Icarus Verilog
$end
$timescale
	1ps
$end
$scope module sr_latch_tb $end
$scope module uut $end
$var wire 1 ! r $end
$var wire 1 " s $end
$var reg 1 # q $end
$var reg 1 $ q_bar $end
$upscope $end
$upscope $end
$enddefinitions $end
$comment Show the parameter values. $end
$dumpall
$end
#10000
$dumpvars
x$
x#
0"
0!
$end
#20000
1$
0#
1!
#30000
0$
1#
0!
1"
#40000
0#
1!
#50000
0!
0"
#60000
1$
1!
#70000
0$
1#
0!
1"
#80000
0#
1!
