day_2/parityGen.v
`timescale 1ns / 1ps

// parity_type = 0 -> even parity
// parity_type = 1 -> odd parity

module parity_gen (data_in, parity_type, gen_parity);

	input [3:0] data_in;
	input parity_type;
	output reg gen_parity;

	// --- generating parity ---
	always @(*) begin
		if (parity_type == 0) begin	// even parity
			gen_parity <= ^data_in;
		end
		else begin
			gen_parity <= ~(^data_in);
		end
	end
endmodule

day_2/parityGenTB.v
`timescale 1ns / 1ps

module parity_gen_tb;

	reg [3:0] data_in;
	reg parity_type;
	wire gen_parity;

	parity_gen uut (.data_in(data_in), .parity_type(parity_type), .gen_parity(gen_parity));

	initial begin
		$dumpfile("parityGenTB.vcd");
		$dumpvars(0, parity_gen_tb);

		$display("\n");
		$monitor("data_in=%b, gen_parity=%b", data_in, gen_parity);

		$display("parity_type=0 (EVEN PARITY)");
		parity_type=1'b0;
		data_in=4'b0000; #10;
		data_in=4'b0011; #10;
		data_in=4'b0110; #10;
		data_in=4'b1000; #10;

		$display("\nTransitioning to other parity");
		data_in=4'bxxxx; #10;

		$display("\nparity_type=1 (ODD PARITY)");
		parity_type=1'b1;
		data_in=4'b0000; #10;
		data_in=4'b0011; #10;
		data_in=4'b0110; #10;
		data_in=4'b1000; #10;

		$display("\n");
		$finish;
	end
endmodule

day_002/parityGenTB.vcd
$date
	Wed Jun 24 00:18:42 2026
$end
$version
	Icarus Verilog
$end
$timescale
	1ps
$end
$scope module parity_gen_tb $end
$var wire 1 ! gen_parity $end
$var reg 4 " data_in [3:0] $end
$var reg 1 # parity_type $end
$scope module uut $end
$var wire 4 $ data_in [3:0] $end
$var wire 1 # parity_type $end
$var reg 1 ! gen_parity $end
$upscope $end
$upscope $end
$enddefinitions $end
$comment Show the parameter values. $end
$dumpall
$end
#0
$dumpvars
b0 $
0#
b0 "
0!
$end
#10000
b11 "
b11 $
#20000
b110 "
b110 $
#30000
1!
b1000 "
b1000 $
#40000
x!
bx "
bx $
#50000
1!
b0 "
b0 $
1#
#60000
b11 "
b11 $
#70000
b110 "
b110 $
#80000
0!
b1000 "
b1000 $
