day_026/uniShiftReg.v
`timescale 1ns / 1ps

module universal_shift_reg #(
	parameter WIDTH = 4
) (
	// ------------------------------
	// clock and reset
	input wire 	       clk_i,
	input wire 	       rst_n_i,	   // async active-low rst

	// ------------------------------
	// inputs
	input wire             wr_en_i,    // if HIGH, allows writing
	input wire [1:0]       sel_i,	   // select lines for 4:1 mux
	input wire [WIDTH-1:0] p_data_i,   // parallel data i/p
	input wire             s_left_i,   // i/p for SHIFTING LEFT
	input wire 	       s_right_i,  // i/p for SHIFTING RIGHT

	// ------------------------------
	// outputs
	output wire 	       s_left_o,   // o/p when SHIFTING LEFT
	output wire	       s_right_o,  // o/p whe SHIFTING RIGHT
	output reg [WIDTH-1:0] p_data_o    // o/p of register
);

	localparam DATA_HOLD     = 2'b00,  // data is held as is
		   SHIFT_RIGHT   = 2'b01,  // data is SHIFTED RIGHT
		   SHIFT_LEFT    = 2'b10,  // data is SHIFTED LEFT
		   PARALLEL_LOAD = 2'b11;  // data is PARALLELLY LOADED to register
	
	always @(posedge clk_i or negedge rst_n_i) begin
		if (!rst_n_i) begin  // register contents reset to `0` on true
			p_data_o <= {WIDTH{1'b0}};
		end
		else begin
			if (wr_en_i) begin  // data can be updated only when `wr_en_i` is HIGH
				case (sel_i)
					DATA_HOLD     : p_data_o <= p_data_o;
					SHIFT_RIGHT   : p_data_o <= {s_right_i, p_data_o[WIDTH-1:1]};
					SHIFT_LEFT    : p_data_o <= {p_data_o[WIDTH-2:0], s_left_i};
					PARALLEL_LOAD : p_data_o <= p_data_i;
					default       : p_data_o <= p_data_o;
				endcase
			end
		end
	end

	assign s_left_o  = p_data_o[WIDTH-1];  // o/p is MSB
	assign s_right_o = p_data_o[0];	       // o/p is LSB

endmodule

day_026/uniShiftRegTB.v
`timescale 1ns / 1ps

module universal_shift_reg_tb;

	// ------------------------
	// parameters
	parameter WIDTH = 4;

	// ------------------------
	// inputs
	reg  		clk_i;
	reg  		rst_n_i;
	reg  		wr_en_i;
	reg [1:0] 	sel_i;
	reg [WIDTH-1:0] p_data_i;
	reg 		s_left_i;
	reg 		s_right_i;

	// ------------------------
	// outputs
	wire 		 s_left_o;
	wire 		 s_right_o;
	wire [WIDTH-1:0] p_data_o;

	// ------------------------
	// other variables
	integer i;
	// string  monitor_var;  --- UNUSED BECAUSE ERROR: "PROPERTY IS NOT IMPLEMENTED"

	universal_shift_reg #(
		.WIDTH(WIDTH)
	) uut (
		.clk_i	   (clk_i),
		.rst_n_i   (rst_n_i),
		.wr_en_i   (wr_en_i),
		.sel_i	   (sel_i),
		.p_data_i  (p_data_i),
		.s_left_i  (s_left_i),
		.s_right_i (s_right_i),
		.s_left_o  (s_left_o),
		.s_right_o (s_right_o),
		.p_data_o  (p_data_o)
	);

	always begin
		#5 clk_i = ~clk_i;
	end

	initial begin
		$timeformat (-9, 0, "", 5);

		// monitor_var = $sformatf(" %%3t |    %%b    |    %%b    |  %%2b  |    %%4b   |     %%b    |     %%b     |    %%0%0db    |     %%b     |     %%b     ", WIDTH);

		$dumpfile ("uniShiftRegTB.vcd");
		$dumpvars (0, universal_shift_reg_tb);

		$display ("\nUNIVERSAL SHIFT REGISTER\n");
		$display (" time | rst_n_i | wr_en_i | sel_i | p_data_i | s_left_i | s_right_i | p_data_o | s_left_o | s_right_o ");
		$display ("------|---------|---------|-------|----------|----------|-----------|----------|----------|-----------");
		$monitor (" %3t  |    %b    |    %b    |  %2b   |   %4b   |     %b    |     %b     |   %4b   |     %b    |     %b    ",$time, rst_n_i, wr_en_i, sel_i, p_data_i, s_left_i, s_right_i, p_data_o, s_left_o, s_right_o);
		// $monitor (monitor_var, $time, rst_n_i, wr_en_i, sel_i, p_data_i, s_left_i, s_right_i, p_data_o, s_left_o, s_right_o);

		clk_i     = 1'b0;
		rst_n_i   = 1'b0;
		wr_en_i   = 1'b0;
		sel_i     = 2'bxx;
		p_data_i  = {WIDTH{1'b0}};
		s_left_i  = 1'b0;
		s_right_i = 1'b0;
	
		@(posedge clk_i);
		@(negedge clk_i);
		rst_n_i  = 1'b1;
		sel_i    = 2'b10;  // SHIFT_LEFT
		s_left_i = 1'b1;

		repeat(2) @(negedge clk_i);
		wr_en_i = 1'b1;

		for (i=0; i<2; i++) begin
			repeat(2) @(negedge clk_i);
			p_data_i = $urandom_range (0, 2**(WIDTH-1)-1);
			sel_i    = 2'b11;  // PARALLEL_LOAD
		end

		repeat(2) @(negedge clk_i);
		sel_i = 2'b01;  // SHIFT_RIGHT, keep s_right_i = 1'b0

		repeat(2) @(negedge clk_i);
		sel_i = 2'b00;  // DATA_HOLD

		@(negedge clk_i);
		#3;

		$display ("\nSIM FIN");
		$finish;
	end

endmodule

day_026/uniShiftRegTB.vcd
$date
	Tue Jul 21 00:08:50 2026
$end
$version
	Icarus Verilog
$end
$timescale
	1ps
$end
$scope module universal_shift_reg_tb $end
$var wire 1 ! s_right_o $end
$var wire 1 " s_left_o $end
$var wire 4 # p_data_o [3:0] $end
$var parameter 32 $ WIDTH $end
$var reg 1 % clk_i $end
$var reg 4 & p_data_i [3:0] $end
$var reg 1 ' rst_n_i $end
$var reg 1 ( s_left_i $end
$var reg 1 ) s_right_i $end
$var reg 2 * sel_i [1:0] $end
$var reg 1 + wr_en_i $end
$var integer 32 , i [31:0] $end
$scope module uut $end
$var wire 1 % clk_i $end
$var wire 4 - p_data_i [3:0] $end
$var wire 1 ' rst_n_i $end
$var wire 1 ( s_left_i $end
$var wire 1 ) s_right_i $end
$var wire 2 . sel_i [1:0] $end
$var wire 1 + wr_en_i $end
$var wire 1 ! s_right_o $end
$var wire 1 " s_left_o $end
$var parameter 2 / DATA_HOLD $end
$var parameter 2 0 PARALLEL_LOAD $end
$var parameter 2 1 SHIFT_LEFT $end
$var parameter 2 2 SHIFT_RIGHT $end
$var parameter 32 3 WIDTH $end
$var reg 4 4 p_data_o [3:0] $end
$upscope $end
$upscope $end
$enddefinitions $end
$comment Show the parameter values. $end
$dumpall
b100 3
b1 2
b10 1
b11 0
b0 /
b100 $
$end
#0
$dumpvars
b0 4
bx .
b0 -
bx ,
0+
bx *
0)
0(
0'
b0 &
0%
b0 #
0"
0!
$end
#5000
1%
#10000
1(
b10 *
b10 .
1'
0%
#15000
1%
#20000
0%
#25000
1%
#30000
b0 ,
1+
0%
#35000
1!
b1 #
b1 4
1%
#40000
0%
#45000
b11 #
b11 4
1%
#50000
b1 ,
b11 *
b11 .
b100 &
b100 -
0%
#55000
0!
b100 #
b100 4
1%
#60000
0%
#65000
1%
#70000
b10 ,
b10 &
b10 -
0%
#75000
b10 #
b10 4
1%
#80000
0%
#85000
1%
#90000
b1 *
b1 .
0%
#95000
1!
b1 #
b1 4
1%
#100000
0%
#105000
0!
b0 #
b0 4
1%
#110000
b0 *
b0 .
0%
