day_025/trinomialLFSR/trinomialLFSR.v
/*
*
* Trinomial LFSR are mostly used for hardware
* efficiency. They use a 2-tap design.
* The polynomial implemented here is 
* x^7 + x^4 + 1
* This will be implemented using a 7-bit
* shift register.
*
*/

module trinomial_lfsr #(
	parameter WIDTH = 7
) (
	input wire 	        clk_i,
	input wire 	        rst_n_i,
	output wire [WIDTH-1:0] lfsr_o
);

	// -----------------------
	// defining shift reg
	reg [WIDTH-1:0] shift_reg;

	always @(posedge clk_i or negedge rst_n_i) begin
		if (!rst_n_i) begin
			shift_reg <= {WIDTH{1'b1}};
		end

		else begin
			shift_reg <= {shift_reg[5:0], shift_reg[6] ^ shift_reg[3]};
		end
	end

	assign lfsr_o = shift_reg;

endmodule

day_025/trinomialLFSR/trinomialLFSRTB.v
`timescale 1ns / 1ps

module trinomial_lfsr_tb;

	reg  		 clk_i;
	reg  		 rst_n_i;
	wire [6:0] lfsr_o;

	trinomial_lfsr uut (
		.clk_i(clk_i),
		.rst_n_i(rst_n_i),
		.lfsr_o(lfsr_o)
	);

	always begin
		#5 clk_i = ~clk_i;
	end

	initial begin
		$timeformat (-9, 0, "", 5);

		$dumpfile ("trinomialLFSRTB.vcd");
		$dumpvars (0, trinomial_lfsr_tb);

		$display ("\nTRINOMIAL LFSR");
		$display ("CHARACTERISTIC POLYNOMIAL: x^7 + x^4 + 1\n");

		$display (" time | rst_n_i | lfsr_o  ");
		$display ("------|---------|---------");
		$monitor ("  %3t |    %b    | %b    ", $time, rst_n_i, lfsr_o);

		clk_i   = 1'b0;
		rst_n_i = 1'b0;

		@(posedge clk_i);
		@(negedge clk_i);
		rst_n_i = 1'b1;

		repeat(10) @(negedge clk_i);
		#3;

		$display ("\nSIM FIN");
		$finish;
	end

endmodule

day_025/trinomialLFSR/trinomialLFSRTB.vcd
$date
	Mon Jul 20 00:12:12 2026
$end
$version
	Icarus Verilog
$end
$timescale
	1ps
$end
$scope module trinomial_lfsr_tb $end
$var wire 7 ! lfsr_o [6:0] $end
$var reg 1 " clk_i $end
$var reg 1 # rst_n_i $end
$scope module uut $end
$var wire 1 " clk_i $end
$var wire 7 $ lfsr_o [6:0] $end
$var wire 1 # rst_n_i $end
$var reg 7 % shift_reg [6:0] $end
$upscope $end
$upscope $end
$enddefinitions $end
$comment Show the parameter values. $end
$dumpall
$end
#0
$dumpvars
b1 %
b1 $
0#
0"
b1 !
$end
#5000
1"
#10000
1#
0"
#15000
b10 !
b10 $
b10 %
1"
#20000
0"
#25000
b100 !
b100 $
b100 %
1"
#30000
0"
#35000
b1000 !
b1000 $
b1000 %
1"
#40000
0"
#45000
b10001 !
b10001 $
b10001 %
1"
#50000
0"
#55000
b100010 !
b100010 $
b100010 %
1"
#60000
0"
#65000
b1000100 !
b1000100 $
b1000100 %
1"
#70000
0"
#75000
b1001 !
b1001 $
b1001 %
1"
#80000
0"
#85000
b10011 !
b10011 $
b10011 %
1"
#90000
0"
#95000
b100110 !
b100110 $
b100110 %
1"
#100000
0"
#105000
b1001100 !
b1001100 $
b1001100 %
1"
