day_012/grayToBinary/grayToBinary.v
`timescale 1ns / 1ps

module gray_to_binary #(
	parameter WIDTH=4
) (
	input  wire [WIDTH-1:0] gray,
	output reg  [WIDTH-1:0] b_out
);

	integer i;

	always @(*) begin
		b_out[WIDTH-1] = gray[WIDTH-1];

		for (i=WIDTH-2; i>=0; i=i-1) begin
			b_out[i] = b_out[i+1] ^ gray[i];
		end
	end

endmodule

day_012/grayToBinary/grayToBinaryTB.v
`timescale 1ns / 1ps

module gray_to_binary_tb;

	parameter WIDTH=4;

	reg  [WIDTH-1:0] gray;
	wire [WIDTH-1:0] b_out;

	integer i;

	gray_to_binary #(
		.WIDTH(WIDTH)
	) uut (
		.gray(gray),
		.b_out(b_out)
	);

	initial begin
		$dumpfile ("grayToBinaryTB.vcd");
		$dumpvars (0, gray_to_binary_tb);

		$display ("\nGRAY TO BINARY CONVERTER\n");
		$monitor ("gray=%b, b_out=%b", gray, b_out);

		for (i=0; i<(1<<WIDTH); i++) begin
			gray = $urandom_range (0, 2**(WIDTH)-1);
			#10;
		end

		$display ("\n");
		$finish;
	end

endmodule

day_012/grayToBinary/grayToBinaryTB.vcd
$date
	Sat Jul  4 01:43:10 2026
$end
$version
	Icarus Verilog
$end
$timescale
	1ps
$end
$scope module gray_to_binary_tb $end
$var wire 4 ! b_out [3:0] $end
$var parameter 32 " WIDTH $end
$var reg 4 # gray [3:0] $end
$var integer 32 $ i [31:0] $end
$scope module uut $end
$var wire 4 % gray [3:0] $end
$var parameter 32 & WIDTH $end
$var reg 4 ' b_out [3:0] $end
$var integer 32 ( i [31:0] $end
$upscope $end
$upscope $end
$enddefinitions $end
$comment Show the parameter values. $end
$dumpall
b100 &
b100 "
$end
#0
$dumpvars
b11111111111111111111111111111111 (
b1110 '
b1001 %
b0 $
b1001 #
b1110 !
$end
#10000
b11111111111111111111111111111111 (
b111 !
b111 '
b100 #
b100 %
b1 $
#20000
b0 !
b0 '
b11111111111111111111111111111111 (
b0 #
b0 %
b10 $
#30000
b10 !
b10 '
b11111111111111111111111111111111 (
b11 #
b11 %
b11 $
#40000
b11111111111111111111111111111111 (
b1111 !
b1111 '
b1000 #
b1000 %
b100 $
#50000
b1000 !
b1000 '
b11111111111111111111111111111111 (
b1100 #
b1100 %
b101 $
#60000
b11111111111111111111111111111111 (
b10 !
b10 '
b11 #
b11 %
b110 $
#70000
b0 !
b0 '
b11111111111111111111111111111111 (
b0 #
b0 %
b111 $
#80000
b11111111111111111111111111111111 (
b1111 !
b1111 '
b1000 #
b1000 %
b1000 $
#90000
b1001 $
#100000
b1101 !
b1101 '
b11111111111111111111111111111111 (
b1011 #
b1011 %
b1010 $
#110000
b1110 !
b1110 '
b11111111111111111111111111111111 (
b1001 #
b1001 %
b1011 $
#120000
b1010 !
b1010 '
b11111111111111111111111111111111 (
b1111 #
b1111 %
b1100 $
#130000
b1000 !
b1000 '
b11111111111111111111111111111111 (
b1100 #
b1100 %
b1101 $
#140000
b1010 !
b1010 '
b11111111111111111111111111111111 (
b1111 #
b1111 %
b1110 $
#150000
b11111111111111111111111111111111 (
b100 !
b100 '
b110 #
b110 %
b1111 $
#160000
b10000 $
