day_3/aluAddSub.v
`timescale 1ns / 1ps

module alu_add_sub #(parameter WIDTH=4)(a, b, cb_in, mode, sum, cb_out);

	input [WIDTH-1:0]      a;
	input [WIDTH-1:0]      b;
	input 		       cb_in;	// Carry in, Borrow in
	input 		       mode;	// 0 = ADD, 1 = SUB
	
	output reg [WIDTH-1:0] sum;
	output reg 	       cb_out;	// Carry out, Borrow out

	always @(*) begin
		if (mode == 1'b0) begin
			// ADD
			{cb_out, sum} = a + b + cb_in;
		end
		else if (mode == 1'b1) begin
			// SUB
			{cb_out, sum} = {1'b0, a} - {1'b0, b} - cb_in;
		end
		else begin
			// explicilty mentioning unknown values
			// REASON: if not done, 'sum' and 'cb_out' will take
			// unknown values, but won't be able to recover from them.
			{cb_out, sum} = {(WIDTH+1){1'bx}};
		end

	end

endmodule

day_3/aluAddSubTB.v
`timescale 1ns / 1ps

module alu_add_sub_tb;

	parameter WIDTH = 4;

	reg [WIDTH-1:0]  a, b;
	reg 		 cb_in, mode;

	wire [WIDTH-1:0] sum;
	wire		 cb_out;

	// variables not part of the uut
	reg [WIDTH-1:0] a_reg [3:0];
	reg [WIDTH-1:0] b_reg [3:0];
	reg [3:0] 	cb_in_reg;

	integer i;						// used in for-loop

	// parameterized uut
	alu_add_sub #(
		.WIDTH(WIDTH)
	) uut (
		.a(a), .b(b), .cb_in(cb_in), .mode(mode),
		.sum(sum), .cb_out(cb_out)
	);

	// passing values
	initial begin
		$dumpfile ("aluAddSubTB.vcd");			// dumpfile which will hold output
		$dumpvars (0, alu_add_sub_tb);			// variables from this file

		$display ("\n");
		$monitor ("a=%b, b=%b, cb_in=%b, sum=%b, cb_out=%b", a, b, cb_in, sum, cb_out);	// monitoring these variables

		$display ("mode=0 (ADD)");
		mode=1'b0;					// setting 'mode' as '0' -> ADD
		for (i=0; i<4; i=i+1) begin
			a = $urandom_range (0, 2**(WIDTH)-1);	// random 4-bit number, range: (0, 15)
			b = $urandom_range (0, 2**(WIDTH)-1);	// random 4-bit number, range: (0, 15)
			cb_in = $urandom_range (0, 1);		// random 1-bit number, range: (0, 1)

			a_reg[i] = a;				// storing these values to...
			b_reg[i] = b;				// ...compare with SUB later
			cb_in_reg[i] = cb_in;

			#10;
		end

		$display ("\nTransitioning from ADD to SUB");
		mode =  1'bx; 					// unknown value while transitioning
		a = {WIDTH{1'bx}};				// assign 1'bx, 'WIDTH' amount of times
		b = {WIDTH{1'bx}};				// assign 1'bx, 'WIDTH' amount of times
		cb_in = 1'bx;
		#10;
		
		$display ("\nmode=1 (SUB)");
		mode=1'b1;					// setting 'mode' as '1' -> SUB
		for (i=0; i<4; i=i+1) begin
			a = a_reg[i];				// using the previously stored values...
			b = b_reg[i];				// ...so that comparison is easier
			cb_in = cb_in_reg[i];
			
			#10;
		end
	
		$display ("\n");
		$finish;
	end

endmodule

day_003/aluAddSubTB.vcd
$date
	Sat Jun 27 13:57:10 2026
$end
$version
	Icarus Verilog
$end
$timescale
	1ps
$end
$scope module alu_add_sub_tb $end
$var wire 4 ! sum [3:0] $end
$var wire 1 " cb_out $end
$var parameter 32 # WIDTH $end
$var reg 4 $ a [3:0] $end
$var reg 4 % b [3:0] $end
$var reg 1 & cb_in $end
$var reg 4 ' cb_in_reg [3:0] $end
$var reg 1 ( mode $end
$var integer 32 ) i [31:0] $end
$scope module uut $end
$var wire 4 * a [3:0] $end
$var wire 4 + b [3:0] $end
$var wire 1 & cb_in $end
$var wire 1 ( mode $end
$var parameter 32 , WIDTH $end
$var reg 1 " cb_out $end
$var reg 4 - sum [3:0] $end
$upscope $end
$upscope $end
$enddefinitions $end
$comment Show the parameter values. $end
$dumpall
b100 ,
b100 #
$end
#0
$dumpvars
b1101 -
b100 +
b1001 *
b0 )
0(
bx0 '
0&
b100 %
b1001 $
0"
b1101 !
$end
#10000
b1100 !
b1100 -
bx10 '
1&
b1000 %
b1000 +
b11 $
b11 *
b1 )
#20000
b100 !
b100 -
bx110 '
b0 %
b0 +
b10 )
#30000
1"
b1110 '
b1011 %
b1011 +
b1000 $
b1000 *
b11 )
#40000
x"
bx !
bx -
x&
bx %
bx +
bx $
bx *
x(
b100 )
#50000
0"
b101 !
b101 -
0&
b100 %
b100 +
b1001 $
b1001 *
b0 )
1(
#60000
1"
b1010 !
b1010 -
1&
b1000 %
b1000 +
b11 $
b11 *
b1 )
#70000
0"
b10 !
b10 -
b0 %
b0 +
b10 )
#80000
1"
b1100 !
b1100 -
b1011 %
b1011 +
b1000 $
b1000 *
b11 )
#90000
b100 )
