day_011/priorityEncoder/priorityEncoder.v
// DECIMAL TO BCD PRIORITY ENCODER

`timescale 1ns / 1ps

module priority_encoder (
	input wire [9:0] a,
	output reg 	 en,
	output reg [3:0] y
);

	always @(*) begin
		y = 4'b0000;
		en = 1'b1;

		casez (a)
			10'b1????????? : y = 4'b1001;
			10'b01???????? : y = 4'b1000;
			10'b001??????? : y = 4'b0111;
			10'b0001?????? : y = 4'b0110;
			10'b00001????? : y = 4'b0101;
			10'b000001???? : y = 4'b0100;
			10'b0000001??? : y = 4'b0011;
			10'b00000001?? : y = 4'b0010;
			10'b000000001? : y = 4'b0001;
			10'b0000000001 : y = 4'b0000;
			default : begin
				y = 4'b0000;
				en = 1'b0;
			end
		endcase
	end

endmodule

day_011/priorityEncoder/priorityEncoderTB.v
`timescale 1ns / 1ps

module priority_encoder_tb;

	reg  [9:0] a;
	wire 	   en;	// enable
	wire [3:0] y;

	integer i;

	priority_encoder uut (.a(a), .en(en), .y(y));

	initial begin
		$dumpfile ("priorityEncoderTB.vcd");
		$dumpvars (0, priority_encoder_tb);

		$display ("\nDECIMAL TO BCD ENCODER\n");
		$monitor ("a=%b, en=%b, y=%b", a, en, y);

		a = 10'b0000000000; #10;
		a = 10'b0000000001; #10;
		a = 10'b0000000011; #10;
		a = 10'b0000000111; #10;
		a = 10'b0000001111; #10;
		a = 10'b0000011111; #10;
		a = 10'b0000111111; #10;
		a = 10'b0001111111; #10;
		a = 10'b0011111111; #10;
		a = 10'b0111111111; #10;
		a = 10'b1111111111; #10;

		$display ("\n");
		$finish;
	end

endmodule

day_011/priorityEncoder/priorityEncoderTB.vcd
$date
	Fri Jul  3 00:07:28 2026
$end
$version
	Icarus Verilog
$end
$timescale
	1ps
$end
$scope module priority_encoder_tb $end
$var wire 4 ! y [3:0] $end
$var wire 1 " en $end
$var reg 10 # a [9:0] $end
$scope module uut $end
$var wire 10 $ a [9:0] $end
$var reg 1 " en $end
$var reg 4 % y [3:0] $end
$upscope $end
$upscope $end
$enddefinitions $end
$comment Show the parameter values. $end
$dumpall
$end
#0
$dumpvars
b0 %
b0 $
b0 #
0"
b0 !
$end
#10000
1"
b1 #
b1 $
#20000
b1 !
b1 %
b11 #
b11 $
#30000
b10 !
b10 %
b111 #
b111 $
#40000
b11 !
b11 %
b1111 #
b1111 $
#50000
b100 !
b100 %
b11111 #
b11111 $
#60000
b101 !
b101 %
b111111 #
b111111 $
#70000
b110 !
b110 %
b1111111 #
b1111111 $
#80000
b111 !
b111 %
b11111111 #
b11111111 $
#90000
b1000 !
b1000 %
b111111111 #
b111111111 $
#100000
b1001 !
b1001 %
b1111111111 #
b1111111111 $
