day_6/multiplier4Bit.v
`timescale 1ns / 1ps

/*
* a3 a2 a1 a0
* b3 b2 b1 b0
* -----------
*  (product)
*
* m0 = {a0b0, a1b0, a2b0, a3b0}
* m1 = {a0b1, a1b1, a2b1, a3b1}
* m2 = {a0b2, a1b2, a2b2, a3b2}
* m3 = {a0b3, a1b3, a2b3, a3b3}
*
* m0 << 1 --> this will LSL m0 by single power of 2, and put '0' as LSB
*/

module multiplier_4bit (
	input [3:0]  a,
	input [3:0]  b,
	output [7:0] p
);

	wire [3:0] m0;
	wire [4:0] m1;
	wire [5:0] m2;
	wire [6:0] m3;	// 7-bit final product after LSL

	wire [7:0] s [2:0];

	assign m0 = {4{b[0]}} & a;
	assign m1 = {4{b[1]}} & a;
	assign m2 = {4{b[2]}} & a;
	assign m3 = {4{b[3]}} & a;

	assign s[0] = m0 + (m1<<1);
	assign s[1] = s[0] + (m2<<2);
	assign s[2] = s[1] + (m3<<3);
	assign p = s[2];

	// assign p = m0 + (m1 << 1) + (m2 << 2) + (m3 << 3);

endmodule

day_6/multiplier4BitTB.v
`timescale 1ns / 1ps

module multiplier_4bit_tb;

	reg [3:0]  a;
	reg [3:0]  b;
	wire [7:0] p;
	
	integer i;

	multiplier_4bit uut (.a(a), .b(b), .p(p));

	initial begin
		$dumpfile ("multiplier4BitTB.vcd");
		$dumpvars (0, multiplier_4bit_tb);

		$display ("\n");
		$monitor ("a=%b, b=%b, p=%b (%b)", a, b, p, p);

		for (i=0; i<8; i+=1) begin
			a = $urandom_range (0, 15);
			b = $urandom_range (0, 15);
			#10;
		end

		$display ("\n");
		$finish;
	end

endmodule

day_6/multiplier4BitTB.vcd
$date
	Sun Jun 28 01:43:39 2026
$end
$version
	Icarus Verilog
$end
$timescale
	1ps
$end
$scope module multiplier_4bit_tb $end
$var wire 8 ! p [7:0] $end
$var reg 4 " a [3:0] $end
$var reg 4 # b [3:0] $end
$var integer 32 $ i [31:0] $end
$scope module uut $end
$var wire 4 % a [3:0] $end
$var wire 4 & b [3:0] $end
$var wire 4 ' m0 [3:0] $end
$var wire 5 ( m1 [4:0] $end
$var wire 6 ) m2 [5:0] $end
$var wire 7 * m3 [6:0] $end
$var wire 8 + p [7:0] $end
$upscope $end
$upscope $end
$enddefinitions $end
$comment Show the parameter values. $end
$dumpall
$end
#0
$dumpvars
b100100 +
b0 *
b1001 )
b0 (
b0 '
b100 &
b1001 %
b0 $
b100 #
b1001 "
b100100 !
$end
#10000
b0 !
b0 +
b0 )
b11 #
b11 &
b0 "
b0 %
b1 $
#20000
b1000 )
b1000 *
b1100000 !
b1100000 +
b0 (
b0 '
b1100 #
b1100 &
b1000 "
b1000 %
b10 $
#30000
b0 !
b0 +
b0 )
b0 *
b0 #
b0 &
b11 "
b11 %
b11 $
#40000
b1000000 !
b1000000 +
b1000 *
b1000 #
b1000 &
b1000 "
b1000 %
b100 $
#50000
b1100011 !
b1100011 +
b1011 '
b1011 *
b1001 #
b1001 &
b1011 "
b1011 %
b101 $
#60000
b1111 )
b10110100 !
b10110100 +
b1111 *
b0 '
b1100 #
b1100 &
b1111 "
b1111 %
b110 $
#70000
b1011010 !
b1011010 +
b1111 (
b0 *
b110 #
b110 &
b111 $
#80000
b1000 $
