day_023/siso/sisoDelayLine.v
`timescale 1ns / 1ps

module siso_delay_line #(
	parameter WIDTH = 16
) (
	input wire  clk_i,
	input wire  rst_n_i,
	input wire  wr_data_i,	// serial in
	output wire rd_data_o	// serial out
);

	// -----------------------
	// defining shift register
	reg [WIDTH-1:0] shift_reg;

	// ------------------------------------------------------------
	// shifting values inside regsiter
	// ------------------------------------------------------------
	always @(posedge clk_i or negedge rst_n_i) begin
		if (!rst_n_i) begin
			shift_reg <= {WIDTH{1'b0}};
		end
		else begin
			shift_reg <= {shift_reg[WIDTH-2:0], wr_data_i};
		end
	end

	assign rd_data_o = shift_reg[WIDTH-1];	// reading from the register

endmodule

day_023/siso/sisoDelayLineTB.v
`timescale 1ns / 1ps

module siso_delay_line_tb;

	// ------------------
	// shift reg size
	parameter WIDTH = 16;

	// ------------
	// i/ps & o/ps
	reg  clk_i;
	reg  rst_n_i;
	reg  wr_data_i;
	wire rd_data_o;

	// ---------------
	// other variables
	integer i;
	
	siso_delay_line #(
		.WIDTH(WIDTH)
	) uut (
		.clk_i(clk_i),
		.rst_n_i(rst_n_i),
		.wr_data_i(wr_data_i),
		.rd_data_o(rd_data_o)
	);

	initial begin
		clk_i = 0;
		forever #1 clk_i = ~clk_i;
	end

	initial begin
		$dumpfile ("sisoDelayLineTB.vcd");
		$dumpvars (0, siso_delay_line_tb);

		$display ("\nSISO: DELAY LINE\n");
		$display (" rst_n_i | wr_data_i | rd_data_o ");
		$display ("---------|-----------|-----------");
		$monitor ("    %b    |     %b     |     %b  ", rst_n_i, wr_data_i, rd_data_o);

		rst_n_i   = 1'b0;
		wr_data_i = 1'b0;

		@(posedge clk_i);
		@(negedge clk_i);
		rst_n_i = 1'b1;

		for (i=0; i<32; i++) begin
			@(negedge clk_i);
			wr_data_i = $urandom_range(0, 1);
		end
		
		@(posedge clk_i);
		#1;	// ends but shows output of last i/p
		
		$display ("\nSIM FIN");
		$finish;
	end

endmodule

day_023/siso/sisoDelayLineTB.vcd
$date
	Sat Jul 18 00:25:34 2026
$end
$version
	Icarus Verilog
$end
$timescale
	1ps
$end
$scope module siso_delay_line_tb $end
$var wire 1 ! rd_data_o $end
$var parameter 32 " WIDTH $end
$var reg 1 # clk_i $end
$var reg 1 $ rst_n_i $end
$var reg 1 % wr_data_i $end
$var integer 32 & i [31:0] $end
$scope module uut $end
$var wire 1 # clk_i $end
$var wire 1 $ rst_n_i $end
$var wire 1 % wr_data_i $end
$var wire 1 ! rd_data_o $end
$var parameter 32 ' WIDTH $end
$var reg 16 ( shift_reg [15:0] $end
$upscope $end
$upscope $end
$enddefinitions $end
$comment Show the parameter values. $end
$dumpall
b10000 '
b10000 "
$end
#0
$dumpvars
b0 (
bx &
0%
0$
0#
0!
$end
#1000
1#
#2000
b0 &
1$
0#
#3000
1#
#4000
b1 &
1%
0#
#5000
b1 (
1#
#6000
b10 &
0%
0#
#7000
b10 (
1#
#8000
b11 &
0#
#9000
b100 (
1#
#10000
b100 &
0#
#11000
b1000 (
1#
#12000
b101 &
1%
0#
#13000
b10001 (
1#
#14000
b110 &
0#
#15000
b100011 (
1#
#16000
b111 &
0%
0#
#17000
b1000110 (
1#
#18000
b1000 &
0#
#19000
b10001100 (
1#
#20000
b1001 &
1%
0#
#21000
b100011001 (
1#
#22000
b1010 &
0#
#23000
b1000110011 (
1#
#24000
b1011 &
0#
#25000
b10001100111 (
1#
#26000
b1100 &
0#
#27000
b100011001111 (
1#
#28000
b1101 &
0#
#29000
b1000110011111 (
1#
#30000
b1110 &
0#
#31000
b10001100111111 (
1#
#32000
b1111 &
0#
#33000
b100011001111111 (
1#
#34000
b10000 &
0%
0#
#35000
1!
b1000110011111110 (
1#
#36000
b10001 &
0#
#37000
0!
b1100111111100 (
1#
#38000
b10010 &
0#
#39000
b11001111111000 (
1#
#40000
b10011 &
1%
0#
#41000
b110011111110001 (
1#
#42000
b10100 &
0%
0#
#43000
1!
b1100111111100010 (
1#
#44000
b10101 &
0#
#45000
b1001111111000100 (
1#
#46000
b10110 &
1%
0#
#47000
0!
b11111110001001 (
1#
#48000
b10111 &
0#
#49000
b111111100010011 (
1#
#50000
b11000 &
0%
0#
#51000
1!
b1111111000100110 (
1#
#52000
b11001 &
0#
#53000
b1111110001001100 (
1#
#54000
b11010 &
0#
#55000
b1111100010011000 (
1#
#56000
b11011 &
1%
0#
#57000
b1111000100110001 (
1#
#58000
b11100 &
0%
0#
#59000
b1110001001100010 (
1#
#60000
b11101 &
0#
#61000
b1100010011000100 (
1#
#62000
b11110 &
0#
#63000
b1000100110001000 (
1#
#64000
b11111 &
0#
#65000
0!
b1001100010000 (
1#
#66000
b100000 &
1%
0#
#67000
b10011000100001 (
1#
